{"categories": {"#0000ff": {"active": true, "id": 9, "name": "个人文化和娱乐服务", "total": 6}, "#3ab11a": {"active": true, "id": 10, "name": "政府服务等", "total": 4}, "#8a6d6d": {"active": true, "id": 3, "name": "建筑服务", "total": 3}, "#98df8a": {"active": true, "id": 7, "name": "特许权使用费和许可费", "total": 3}, "#9edae5": {"active": true, "id": 8, "name": "其他商业服务", "total": 18}, "#D1FF00": {"active": true, "id": 2, "name": "通讯服务", "total": 5}, "#FFC41C": {"active": true, "id": 1, "name": "旅行", "total": 8}, "#FFE999": {"active": true, "id": 0, "name": "运输", "total": 25}, "#e377c2": {"active": true, "id": 4, "name": "保险服务", "total": 6}, "#f7b6d2": {"active": true, "id": 6, "name": "计算机和信息服务", "total": 3}, "#ff0000": {"active": true, "id": 5, "name": "金融服务", "total": 1}, "#ffff00": {"active": true, "id": 11, "name": "其他服务", "total": 4}}, "countries": {"AE": {"area": 83600, "continent": 2, "exports": 3868.099034309387, "id": 2, "iso": "ARE", "lat": "54", "lon": "24", "name": "阿拉伯联合酋长国", "particles": 32, "polygons": [10], "polygons3D": [307], "products": {"200": 2076.02, "205": 238.287, "236": 12.76, "249": 158.707, "253": 15.95, "266": 30.306, "268": 278.191, "269": 82.0, "981": 491.13, "982": 484.75}, "sub": 14}, "AL": {"area": 28748, "continent": 4, "exports": 493.76799392700195, "id": 1, "iso": "ALB", "lat": "20", "lon": "41", "name": "阿尔巴尼亚", "particles": 4, "polygons": [9], "polygons3D": [306], "products": {"200": 247.84, "236": 196.673, "981": 26.039, "982": 23.216}, "sub": 17}, "AO": {"area": 1246700, "continent": 1, "exports": 536.8250102996826, "id": 0, "iso": "AGO", "lat": "18.5", "lon": "-12.5", "name": "安哥拉", "particles": 4, "polygons": [7, 8], "polygons3D": [304, 305], "products": {"200": 536.825}, "sub": 2}, "AR": {"area": 2780400, "continent": 5, "exports": 3488.5609970092773, "id": 3, "iso": "ARG", "lat": "-64", "lon": "-34", "name": "阿根廷", "particles": 29, "polygons": [11, 12], "polygons3D": [308, 309], "products": {"200": 1418.28, "205": 234.249, "206": 93.144, "208": 28.66, "210": 142.404, "211": 66.276, "212": 10.747, "236": 373.516, "247": 17.0, "249": 18.808, "253": 101.41, "257": 48.364, "262": 10.398, "268": 94.937, "269": 14.33, "270": 12.539, "273": 27.704, "284": 11.643, "291": 14.0, "981": 450.75, "982": 299.401}, "sub": 8}, "AT": {"area": 83871, "continent": 4, "exports": 65547.85906028748, "id": 5, "iso": "AUT", "lat": "13.333", "lon": "47.333333", "name": "奥地利", "particles": 546, "polygons": [25], "polygons3D": [322], "products": {"200": 19951.1, "205": 4028.1, "236": 6215.03, "245": 576.915, "246": 106.0, "247": 222.0, "249": 593.856, "253": 389.629, "260": 453.646, "262": 320.926, "266": 171.286, "268": 5572.43, "269": 273.0, "272": 35.0, "273": 2365.55, "274": 182.933, "277": 181.343, "278": 430.302, "279": 559.974, "280": 999.481, "284": 38.0, "287": 101.643, "291": 13.176, "981": 9216.11, "982": 8524.6, "983": 4025.82}, "sub": 18}, "AU": {"area": 7692024, "continent": 3, "exports": 46590.86291408539, "id": 4, "iso": "AUS", "lat": "135", "lon": "-25", "name": "澳大利亚", "particles": 388, "polygons": [23, 24], "polygons3D": [320, 321], "products": {"200": 16865.1, "205": 4118.74, "206": 1087.29, "208": 103.892, "210": 924.284, "211": 65.381, "213": 14.33, "214": 35.825, "236": 5451.21, "245": 414.424, "247": 43.0, "249": 23.286, "250": 10.747, "253": 303.475, "257": 24.182, "260": 237.221, "262": 384.87, "263": 47.468, "266": 1132.64, "268": 2018.9, "269": 482.133, "270": 110.162, "273": 135.118, "274": 30.808, "277": 29.017, "280": 24.182, "284": 61.798, "287": 509.866, "291": 194.503, "891": 49.259, "981": 6162.03, "982": 5382.15, "983": 113.565}, "sub": 19}, "AZ": {"area": 86600, "continent": 4, "exports": 668.3170051574707, "id": 6, "iso": "AZE", "lat": "47.5", "lon": "40.5", "name": "阿塞拜疆", "particles": 5, "polygons": [26, 27], "polygons3D": [323, 324], "products": {"200": 351.95, "205": 128.747, "236": 89.964, "249": 23.208, "981": 37.224, "982": 37.224}, "sub": 14}, "BA": {"area": 51209, "continent": 4, "exports": 153.87599563598633, "id": 10, "iso": "BIH", "lat": "17.833333", "lon": "44.25", "name": "波斯尼亚和黑塞哥维那", "particles": 1, "polygons": [37], "polygons3D": [334], "products": {"200": 134.112, "236": 19.764}, "sub": 17}, "BD": {"area": 147570, "continent": 2, "exports": 493.085000038147, "id": 8, "iso": "BGD", "lat": "90", "lon": "24", "name": "孟加拉国", "particles": 4, "polygons": [32], "polygons3D": [329], "products": {"200": 159.085, "205": 36.0, "268": 74.0, "269": 74.0, "981": 75.0, "982": 75.0}, "sub": 12}, "BE": {"area": 30528, "continent": 4, "exports": 90688.61571788788, "id": 7, "iso": "BEL", "lat": "4", "lon": "50.833333", "name": "比利时", "particles": 755, "polygons": [29], "polygons3D": [326], "products": {"200": 33789.7, "205": 5610.63, "206": 1007.58, "208": 929.656, "209": 10.747, "210": 277.643, "211": 91.354, "212": 100.31, "213": 39.407, "214": 181.812, "216": 36.721, "219": 14.33, "221": 12.539, "223": 143.3, "225": 30.451, "236": 8889.24, "237": 77.024, "240": 483.637, "243": 472.889, "245": 435.325, "246": 31.226, "247": 305.795, "249": 131.676, "253": 59.303, "256": 11.643, "260": 267.615, "262": 541.181, "263": 430.795, "266": 438.388, "268": 4313.57, "269": 664.263, "271": 55.529, "272": 87.841, "273": 2890.42, "274": 448.711, "277": 369.0, "278": 1495.37, "279": 306.802, "280": 257.706, "284": 117.623, "285": 1142.81, "287": 69.859, "288": 64.485, "291": 199.546, "981": 16834.5, "982": 6518.63}, "sub": 18}, "BG": {"area": 110879, "continent": 4, "exports": 2142.3239936828613, "id": 9, "iso": "BGR", "lat": "25", "lon": "43", "name": "保加利亚", "particles": 17, "polygons": [33], "polygons3D": [330], "products": {"200": 852.989, "205": 102.967, "210": 42.094, "211": 12.539, "214": 10.747, "236": 336.932, "253": 16.936, "268": 127.505, "269": 12.551, "273": 30.554, "280": 11.643, "981": 324.278, "982": 260.589}, "sub": 15}, "BO": {"area": 1098581, "continent": 5, "exports": 30.25, "id": 12, "iso": "BOL", "lat": "-65", "lon": "-17", "name": "玻利维亚", "particles": 0, "polygons": [41], "polygons3D": [338], "products": {"200": 30.25}, "sub": 8}, "BR": {"area": 8515767, "continent": 5, "exports": 13947.068014144897, "id": 13, "iso": "BRA", "lat": "-55", "lon": "-10", "name": "巴西", "particles": 116, "polygons": [42], "polygons3D": [339], "products": {"200": 5433.42, "205": 954.428, "206": 420.047, "208": 91.354, "210": 494.384, "211": 128.97, "212": 18.808, "213": 47.468, "214": 25.973, "216": 10.747, "223": 21.495, "236": 1457.43, "245": 10.747, "247": 80.0, "249": 253.461, "250": 42.094, "253": 96.889, "257": 16.121, "260": 28.481, "262": 64.484, "263": 53.737, "266": 71.11, "268": 588.708, "269": 69.155, "270": 48.364, "272": 15.226, "273": 120.909, "274": 13.434, "277": 10.747, "280": 28.66, "284": 30.451, "285": 17.017, "287": 31.043, "291": 17.0, "891": 23.286, "981": 1497.18, "982": 1242.11, "983": 372.132}, "sub": 8}, "BY": {"area": 207600, "continent": 4, "exports": 1598.5009899139404, "id": 11, "iso": "BLR", "lat": "28", "lon": "53", "name": "白俄罗斯", "particles": 13, "polygons": [38], "polygons3D": [335], "products": {"200": 797.553, "205": 84.87, "236": 293.238, "245": 28.518, "268": 75.25, "981": 162.22, "982": 156.852}, "sub": 15}, "CA": {"area": 9984670, "continent": 6, "exports": 144633.3862848282, "id": 14, "iso": "CAN", "lat": "-96", "lon": "60", "name": "加拿大", "particles": 1205, "polygons": [47, 48, 49, 50, 51, 52, 53, 54, 55, 56, 57, 58, 59, 60, 61, 62, 63, 64, 65, 66, 67, 68, 69, 70, 71, 72, 73, 74, 75, 76], "polygons3D": [344, 345, 346, 347, 348, 349, 350, 351, 352, 353, 354, 355, 356, 357, 358, 359, 360, 361, 362, 363, 364, 365, 366, 367, 368, 369, 370, 371, 372, 373], "products": {"200": 43679.6, "205": 5770.45, "206": 1079.23, "207": 35.825, "208": 228.384, "209": 33.138, "210": 1376.57, "211": 792.626, "212": 72.545, "213": 234.654, "214": 136.135, "215": 10.747, "216": 11.643, "217": 27.764, "218": 50.155, "223": 11.643, "225": 11.643, "232": 27.764, "236": 10834.9, "237": 107.475, "239": 60.902, "240": 360.936, "243": 267.791, "245": 1038.4, "247": 271.256, "249": 61.892, "250": 25.973, "253": 2063.48, "257": 13.434, "260": 1538.11, "262": 1338.83, "263": 77.024, "264": 417.091, "266": 3811.12, "268": 8549.2, "269": 817.413, "270": 353.771, "271": 29.555, "272": 394.628, "273": 6853.89, "274": 2699.59, "275": 304.381, "277": 2251.02, "278": 250.255, "279": 509.424, "280": 820.023, "282": 154.738, "284": 1981.77, "285": 76.128, "287": 1371.87, "291": 349.604, "292": 11.643, "293": 68.067, "891": 29.556, "892": 27.764, "981": 20563.9, "982": 19944.1, "983": 342.04}, "sub": 9}, "CG": {"area": 342000, "continent": 1, "exports": 132.27600193023682, "id": 20, "iso": "COG", "lat": "15", "lon": "-1", "name": "刚果共和国", "particles": 1, "polygons": [85], "polygons3D": [382], "products": {"200": 132.276}, "sub": 2}, "CH": {"area": 41284, "continent": 4, "exports": 162708.46311569214, "id": 15, "iso": "CHE", "lat": "8", "lon": "47", "name": "瑞士", "particles": 1355, "polygons": [77], "polygons3D": [374], "products": {"200": 44335.5, "205": 3778.92, "206": 1571.82, "207": 11.643, "208": 783.671, "209": 305.408, "210": 920.702, "211": 427.212, "212": 93.144, "213": 174.646, "214": 1416.88, "215": 78.815, "216": 551.704, "217": 179.124, "218": 17.912, "219": 340.336, "220": 136.135, "221": 72.546, "222": 21.495, "223": 617.98, "225": 415.569, "226": 120.909, "227": 36.721, "229": 36.721, "231": 17.912, "232": 60.901, "236": 10206.6, "237": 431.69, "238": 17.912, "239": 209.576, "240": 1916.63, "241": 18.808, "242": 27.764, "243": 1715.12, "245": 402.037, "246": 17.017, "247": 221.306, "249": 395.457, "250": 188.977, "251": 11.643, "253": 2776.24, "255": 14.33, "256": 27.764, "257": 139.717, "260": 3587.5, "262": 1275.91, "263": 1223.42, "266": 2994.47, "268": 10672.1, "269": 1792.99, "270": 555.287, "271": 649.326, "272": 144.658, "273": 4796.49, "274": 1273.84, "276": 15.226, "277": 751.438, "278": 564.088, "279": 294.414, "280": 491.574, "281": 80.606, "283": 76.128, "284": 610.716, "285": 657.387, "287": 558.3, "288": 97.623, "289": 166.586, "891": 345.711, "892": 104.788, "897": 82.397, "981": 25828.4, "982": 22916.0, "983": 4838.25}, "sub": 18}, "CI": {"area": 322463, "continent": 1, "exports": 244.2940092086792, "id": 18, "iso": "CIV", "lat": "-5", "lon": "8", "name": "科特迪瓦", "particles": 2, "polygons": [82], "polygons3D": [379], "products": {"200": 244.294}, "sub": 5}, "CL": {"area": 756102, "continent": 5, "exports": 3421.940011024475, "id": 16, "iso": "CHL", "lat": "-71", "lon": "-30", "name": "智利", "particles": 28, "polygons": [78, 79], "polygons3D": [375, 376], "products": {"200": 1482.78, "205": 377.698, "206": 209.576, "208": 110.162, "210": 53.737, "213": 14.33, "214": 11.643, "236": 360.535, "245": 12.235, "247": 30.0, "249": 17.912, "250": 17.912, "253": 52.842, "257": 25.077, "268": 78.816, "273": 26.336, "280": 16.121, "981": 318.874, "982": 193.349, "983": 12.001}, "sub": 8}, "CM": {"area": 475442, "continent": 1, "exports": 326.08298778533936, "id": 19, "iso": "CMR", "lat": "12", "lon": "6", "name": "喀麦隆", "particles": 2, "polygons": [83], "polygons3D": [380], "products": {"200": 326.083}, "sub": 2}, "CN": {"area": 9706961, "continent": 2, "exports": 80871.39487838745, "id": 17, "iso": "CHN", "lat": "105", "lon": "35", "name": "中国", "particles": 673, "polygons": [80, 81], "polygons3D": [377, 378], "products": {"200": 29248.8, "205": 10628.4, "236": 7741.69, "245": 232.667, "247": 49.0, "249": 516.77, "253": 201.574, "260": 136.043, "262": 225.916, "266": 729.056, "268": 6641.4, "269": 4838.95, "272": 28.359, "273": 731.009, "274": 261.015, "275": 15.0, "276": 62.0, "277": 184.015, "278": 132.0, "279": 38.757, "280": 211.39, "284": 70.898, "287": 48.001, "291": 79.8, "981": 8963.16, "982": 8855.78}, "sub": 11}, "CO": {"area": 1141748, "continent": 5, "exports": 948.3519973754883, "id": 21, "iso": "COL", "lat": "-72", "lon": "4", "name": "哥伦比亚", "particles": 7, "polygons": [86], "polygons3D": [383], "products": {"200": 485.403, "205": 62.694, "206": 28.66, "210": 28.66, "236": 38.331, "253": 52.842, "268": 25.077, "981": 117.373, "982": 109.312}, "sub": 8}, "CR": {"area": 51100, "continent": 6, "exports": 48.91499900817871, "id": 22, "iso": "CRI", "lat": "-84", "lon": "10", "name": "哥斯达黎加", "particles": 0, "polygons": [87], "polygons3D": [384], "products": {"200": 48.915}, "sub": 7}, "CU": {"area": 109884, "continent": 6, "exports": 268.51799392700195, "id": 23, "iso": "CUB", "lat": "-79.5", "lon": "22", "name": "古巴", "particles": 2, "polygons": [88], "polygons3D": [385], "products": {"200": 268.518}, "sub": 6}, "CZ": {"area": 78865, "continent": 4, "exports": 10810.777981758118, "id": 24, "iso": "CZE", "lat": "15", "lon": "49.75", "name": "捷克共和国", "particles": 90, "polygons": [91], "polygons3D": [388], "products": {"200": 3981.84, "205": 312.571, "214": 140.612, "219": 23.286, "223": 13.434, "231": 63.589, "232": 12.539, "236": 1402.4, "237": 34.929, "239": 34.929, "240": 61.798, "242": 16.121, "243": 38.512, "245": 45.0, "247": 38.0, "249": 100.286, "253": 30.451, "257": 14.33, "260": 14.33, "262": 37.434, "263": 11.643, "266": 19.704, "268": 635.24, "269": 105.859, "272": 10.0, "273": 320.273, "274": 69.286, "275": 18.808, "277": 46.0, "278": 32.0, "279": 22.0, "280": 48.0, "284": 81.502, "287": 13.434, "981": 1927.45, "982": 1033.19}, "sub": 15}, "DE": {"area": 357114, "continent": 4, "exports": 468501.77704811096, "id": 25, "iso": "DEU", "lat": "10.5", "lon": "51.5", "name": "德国", "particles": 3904, "polygons": [92], "polygons3D": [389], "products": {"200": 134564.0, "205": 17078.7, "206": 3532.34, "208": 1870.06, "209": 1499.27, "210": 3544.88, "211": 2526.55, "212": 109.267, "213": 758.594, "214": 1650.64, "215": 137.03, "216": 234.654, "217": 1213.57, "219": 85.084, "220": 66.276, "222": 18.808, "223": 79.711, "225": 79.711, "231": 31.347, "232": 1278.05, "236": 44247.5, "237": 1531.52, "238": 122.7, "239": 1407.02, "240": 7572.5, "241": 49.259, "242": 322.424, "243": 7183.8, "245": 2528.48, "246": 642.98, "247": 1796.46, "249": 3403.3, "250": 1115.05, "251": 92.249, "253": 4275.8, "255": 68.067, "256": 26.869, "257": 764.863, "260": 2978.62, "262": 5072.38, "263": 2536.41, "264": 28.66, "266": 4574.31, "268": 28828.1, "269": 5329.73, "271": 2239.06, "272": 807.285, "273": 20846.1, "274": 6710.08, "277": 5440.08, "278": 1947.89, "279": 4563.49, "280": 3367.84, "284": 2214.37, "285": 1700.79, "287": 1625.99, "288": 1372.99, "291": 1512.08, "292": 10.747, "294": 351.084, "891": 1647.05, "892": 1633.62, "981": 59727.2, "982": 53926.3}, "sub": 18}, "DK": {"area": 43094, "continent": 4, "exports": 48813.23406982422, "id": 26, "iso": "DNK", "lat": "10", "lon": "56", "name": "丹麦", "particles": 406, "polygons": [94, 95], "polygons3D": [391, 392], "products": {"200": 21274.4, "205": 9781.58, "206": 4569.47, "236": 5119.21, "245": 63.0, "247": 54.0, "249": 47.0, "253": 11.0, "262": 31.0, "266": 73.705, "268": 1186.44, "269": 80.235, "272": 31.176, "273": 214.0, "274": 69.0, "277": 69.0, "278": 24.0, "279": 33.0, "280": 85.0, "291": 10.0, "981": 4530.42, "982": 1456.61}, "sub": 16}, "DO": {"area": 48671, "continent": 6, "exports": 201.556001663208, "id": 27, "iso": "DOM", "lat": "-70.666667", "lon": "19", "name": "多明尼加共和国", "particles": 1, "polygons": [96], "polygons3D": [393], "products": {"200": 201.556}, "sub": 6}, "DZ": {"area": 2381741, "continent": 1, "exports": 2167.632972717285, "id": 28, "iso": "DZA", "lat": "3", "lon": "28", "name": "阿尔及利亚", "particles": 18, "polygons": [97], "polygons3D": [394], "products": {"200": 2111.02, "236": 56.616}, "sub": 3}, "EC": {"area": 276841, "continent": 5, "exports": 77.39799880981445, "id": 29, "iso": "ECU", "lat": "-77.5", "lon": "-2", "name": "厄瓜多尔", "particles": 0, "polygons": [98], "polygons3D": [395], "products": {"200": 77.398}, "sub": 8}, "EE": {"area": 45227, "continent": 4, "exports": 1421.972996711731, "id": 32, "iso": "EST", "lat": "26", "lon": "59", "name": "爱沙尼亚", "particles": 11, "polygons": [102], "polygons3D": [399], "products": {"200": 573.246, "205": 175.998, "214": 10.747, "236": 93.251, "245": 12.235, "262": 11.829, "268": 74.892, "273": 54.072, "278": 36.648, "981": 248.517, "982": 130.538}, "sub": 16}, "EG": {"area": 1002450, "continent": 1, "exports": 4609.901008605957, "id": 30, "iso": "EGY", "lat": "30", "lon": "27", "name": "埃及", "particles": 38, "polygons": [99], "polygons3D": [396], "products": {"200": 1512.63, "205": 201.302, "206": 142.404, "210": 145.092, "211": 17.912, "214": 13.434, "236": 254.312, "245": 34.23, "249": 68.067, "250": 15.226, "253": 23.286, "260": 14.33, "268": 489.602, "269": 39.407, "270": 34.929, "273": 36.721, "280": 20.599, "284": 12.539, "291": 28.402, "981": 800.341, "982": 676.473, "983": 28.66}, "sub": 3}, "ES": {"area": 505992, "continent": 4, "exports": 71626.31302642822, "id": 31, "iso": "ESP", "lat": "-4", "lon": "40", "name": "西班牙", "particles": 596, "polygons": [101], "polygons3D": [398], "products": {"200": 33971.3, "205": 7221.91, "206": 14.33, "208": 14.33, "236": 6330.64, "245": 232.469, "247": 238.117, "249": 118.0, "253": 21.2, "260": 42.0, "262": 58.0, "266": 47.0, "268": 1179.56, "269": 235.294, "273": 661.0, "274": 104.0, "277": 104.0, "278": 225.0, "279": 122.0, "280": 193.0, "284": 17.0, "287": 10.0, "291": 21.0, "981": 18732.5, "982": 1712.66}, "sub": 17}, "ET": {"area": 1104300, "continent": 1, "exports": 71.76000022888184, "id": 33, "iso": "ETH", "lat": "38", "lon": "8", "name": "埃塞俄比亚", "particles": 0, "polygons": [103], "polygons3D": [400], "products": {"200": 71.76}, "sub": 1}, "FI": {"area": 338424, "continent": 4, "exports": 27625.67704296112, "id": 34, "iso": "FIN", "lat": "26", "lon": "64", "name": "芬兰", "particles": 230, "polygons": [104], "polygons3D": [401], "products": {"200": 8692.4, "205": 1698.57, "206": 316.154, "208": 308.095, "210": 81.5, "211": 56.423, "214": 51.946, "216": 50.155, "219": 14.33, "221": 13.434, "223": 34.929, "225": 34.929, "236": 1764.89, "237": 119.118, "240": 260.625, "245": 154.12, "246": 16.94, "247": 114.775, "249": 235.332, "250": 108.37, "253": 93.172, "262": 90.883, "263": 58.215, "266": 415.355, "268": 1131.88, "269": 209.025, "271": 53.737, "272": 221.079, "273": 780.37, "274": 54.973, "277": 40.643, "278": 138.787, "279": 351.424, "280": 46.0, "284": 14.33, "285": 103.892, "287": 17.017, "288": 16.121, "291": 40.363, "292": 18.808, "891": 10.747, "892": 334.068, "981": 4554.33, "982": 2314.79, "983": 2388.63}, "sub": 16}, "FR": {"area": 551695, "continent": 4, "exports": 170941.88281917572, "id": 35, "iso": "FRA", "lat": "2", "lon": "46", "name": "法国", "particles": 1424, "polygons": [109, 110], "polygons3D": [406, 407], "products": {"200": 63764.0, "205": 9961.08, "206": 2148.6, "208": 969.064, "209": 408.404, "210": 3305.75, "211": 575.887, "212": 670.822, "213": 875.025, "214": 945.778, "218": 102.997, "219": 148.673, "220": 50.155, "232": 17.912, "236": 16254.1, "245": 588.453, "246": 14.0, "247": 411.0, "249": 712.966, "253": 511.512, "257": 200.62, "260": 730.683, "262": 945.121, "264": 13.0, "266": 1420.88, "268": 8729.98, "269": 1297.09, "271": 463.037, "272": 637.05, "273": 5234.05, "274": 698.0, "277": 698.0, "278": 510.544, "279": 463.936, "280": 484.085, "284": 80.234, "285": 584.842, "287": 751.432, "288": 530.209, "289": 99.414, "291": 172.581, "981": 28919.1, "982": 14841.8}, "sub": 18}, "GA": {"area": 267668, "continent": 1, "exports": 341.2550048828125, "id": 36, "iso": "GAB", "lat": "11.75", "lon": "-1", "name": "加蓬", "particles": 2, "polygons": [111], "polygons3D": [408], "products": {"200": 341.255}, "sub": 2}, "GB": {"area": 242900, "continent": 4, "exports": 279649.90145874023, "id": 37, "iso": "GBR", "lat": "-4", "lon": "54", "name": "英国", "particles": 2330, "polygons": [112, 113], "polygons3D": [409, 410], "products": {"200": 102000.0, "205": 17275.8, "206": 2961.83, "207": 25.973, "208": 758.594, "209": 639.475, "210": 5168.65, "211": 1081.91, "212": 159.421, "213": 1729.45, "214": 246.297, "236": 36100.3, "245": 643.111, "246": 14.0, "247": 481.294, "249": 549.983, "253": 663.113, "260": 3022.76, "262": 1161.31, "264": 26.441, "266": 3300.72, "268": 14196.4, "269": 1292.65, "272": 51.0, "273": 7821.23, "274": 2334.25, "275": 16.0, "277": 1365.0, "278": 1110.05, "279": 628.176, "280": 947.236, "284": 1344.31, "287": 935.972, "291": 951.928, "292": 51.946, "293": 795.314, "958": 56.425, "959": 36.721, "981": 42912.3, "982": 24792.4}, "sub": 16}, "GE": {"area": 69700, "continent": 4, "exports": 69.95300102233887, "id": 38, "iso": "GEO", "lat": "43.499", "lon": "41.999981", "name": "格鲁吉亚", "particles": 0, "polygons": [114], "polygons3D": [411], "products": {"200": 69.953}, "sub": 14}, "GH": {"area": 238533, "continent": 1, "exports": 44.3829984664917, "id": 39, "iso": "GHA", "lat": "-2", "lon": "8", "name": "加纳", "particles": 0, "polygons": [115], "polygons3D": [412], "products": {"200": 44.383}, "sub": 5}, "GN": {"area": 245857, "continent": 1, "exports": 65.22599792480469, "id": 40, "iso": "GIN", "lat": "-10", "lon": "11", "name": "几内亚", "particles": 0, "polygons": [116], "polygons3D": [413], "products": {"200": 65.226}, "sub": 5}, "GR": {"area": 131990, "continent": 4, "exports": 19290.737942695618, "id": 41, "iso": "GRC", "lat": "22", "lon": "39", "name": "希腊", "particles": 160, "polygons": [120, 121], "polygons3D": [417, 418], "products": {"200": 8951.43, "205": 3609.35, "236": 2371.48, "245": 121.451, "247": 119.451, "249": 41.0, "253": 95.43, "260": 12.293, "262": 27.422, "266": 87.941, "268": 487.799, "269": 69.238, "273": 214.974, "274": 87.0, "277": 87.0, "278": 29.293, "279": 25.238, "280": 27.0, "284": 44.443, "287": 66.192, "291": 207.338, "981": 1373.73, "982": 1134.25}, "sub": 17}, "GT": {"area": 108889, "continent": 6, "exports": 48.273000717163086, "id": 42, "iso": "GTM", "lat": "-90.25", "lon": "15.5", "name": "危地马拉", "particles": 0, "polygons": [123], "polygons3D": [420], "products": {"200": 48.273}, "sub": 7}, "HK": {"area": 1104, "continent": 2, "exports": 68615.94609260559, "id": 43, "iso": "HKG", "lat": "114.12", "lon": "22.25", "name": "中国香港", "particles": 571, "products": {"200": 25086.6, "205": 4808.0, "206": 1557.49, "208": 221.219, "210": 1189.39, "211": 51.946, "212": 91.354, "213": 83.293, "214": 37.616, "223": 10.747, "236": 11121.8, "245": 655.0, "247": 34.0, "249": 219.429, "250": 19.704, "253": 520.0, "257": 66.276, "260": 630.41, "262": 176.0, "263": 10.747, "264": 10.0, "266": 620.0, "268": 2862.97, "269": 1654.65, "270": 33.138, "272": 187.0, "273": 1046.37, "274": 584.017, "275": 25.0, "276": 44.0, "277": 468.0, "278": 339.0, "284": 10.747, "285": 38.512, "287": 34.747, "291": 63.017, "981": 7797.64, "982": 5965.51, "983": 240.654}, "sub": 11}, "HN": {"area": 112492, "continent": 5, "exports": 9036805590.326, "id": 44, "iso": "HND", "lat": "-86.5", "lon": "15", "name": "洪都拉斯", "particles": 0, "polygons": [126], "polygons3D": [423], "products": {}, "sub": 7}, "HR": {"area": 56594, "continent": 4, "exports": 6350.5360107421875, "id": 45, "iso": "HRV", "lat": "15.5", "lon": "45.166667", "name": "克罗地亚", "particles": 52, "polygons": [127], "polygons3D": [424], "products": {"200": 2167.5, "205": 162.108, "206": 11.643, "210": 104.788, "211": 64.485, "213": 13.434, "214": 66.275, "216": 23.286, "217": 12.539, "219": 11.643, "223": 17.912, "225": 17.017, "231": 10.747, "236": 904.595, "240": 174.647, "243": 172.855, "245": 11.294, "260": 12.539, "262": 11.643, "266": 16.121, "268": 300.979, "269": 54.633, "273": 112.849, "278": 10.747, "981": 964.202, "982": 512.543, "983": 407.509}, "sub": 17}, "HU": {"area": 93028, "continent": 4, "exports": 13893.944032669067, "id": 46, "iso": "HUN", "lat": "20", "lon": "47", "name": "匈牙利", "particles": 115, "polygons": [129], "polygons3D": [426], "products": {"200": 4751.76, "205": 777.402, "214": 33.138, "223": 14.33, "232": 10.747, "236": 714.365, "245": 39.121, "247": 20.0, "249": 51.0, "253": 37.616, "260": 28.66, "262": 71.627, "266": 190.767, "268": 735.002, "269": 24.0, "272": 66.276, "273": 539.412, "274": 45.0, "277": 45.0, "278": 17.0, "279": 14.0, "280": 118.0, "287": 345.711, "288": 340.337, "291": 36.391, "981": 3165.24, "982": 1662.04}, "sub": 15}, "ID": {"area": 1904569, "continent": 2, "exports": 10636.18895149231, "id": 47, "iso": "IDN", "lat": "120", "lon": "-5", "name": "印度尼西亚", "particles": 88, "polygons": [130, 131, 132, 133, 134, 135, 136, 137, 138, 139, 140, 141, 142], "polygons3D": [427, 428, 429, 430, 431, 432, 433, 434, 435, 436, 437, 438, 439], "products": {"200": 4320.31, "205": 711.278, "206": 393.178, "208": 32.242, "210": 311.677, "211": 25.973, "236": 809.818, "247": 21.0, "249": 129.865, "250": 34.929, "253": 108.037, "260": 40.66, "262": 67.172, "263": 67.172, "266": 177.207, "268": 610.614, "269": 160.842, "270": 15.226, "273": 24.232, "287": 17.707, "291": 38.336, "981": 1290.66, "982": 1228.06}, "sub": 13}, "IE": {"area": 70273, "continent": 4, "exports": 115049.30792427063, "id": 49, "iso": "IRL", "lat": "-8", "lon": "53", "name": "爱尔兰", "particles": 958, "polygons": [144], "polygons3D": [441], "products": {"200": 35841.8, "205": 1260.3, "236": 2564.67, "240": 314.364, "243": 314.364, "245": 97.633, "247": 95.633, "249": 23.0, "253": 911.071, "254": 154.047, "256": 328.693, "260": 589.569, "262": 1373.29, "263": 43.886, "266": 6967.22, "268": 6774.94, "269": 1732.27, "271": 180.916, "272": 177.703, "273": 3148.53, "274": 130.963, "277": 62.0, "278": 546.209, "279": 1579.55, "280": 45.0, "284": 751.428, "285": 767.549, "287": 27.0, "981": 31416.9, "982": 16828.8}, "sub": 16}, "IL": {"area": 20770, "continent": 2, "exports": 9359.51001739502, "id": 51, "iso": "ISR", "lat": "34.75", "lon": "31.5", "name": "以色列", "particles": 77, "polygons": [148], "polygons3D": [445], "products": {"200": 3459.03, "205": 1164.11, "206": 138.823, "208": 53.737, "210": 297.347, "211": 94.04, "212": 12.539, "214": 12.539, "236": 989.991, "240": 27.765, "243": 27.765, "245": 10.747, "247": 20.0, "249": 55.529, "250": 35.825, "253": 185.394, "257": 99.414, "260": 25.973, "262": 11.643, "263": 11.643, "266": 46.121, "268": 452.107, "269": 94.752, "270": 36.721, "273": 51.946, "285": 25.077, "981": 992.316, "982": 884.517, "983": 42.094}, "sub": 14}, "IN": {"area": 3287590, "continent": 2, "exports": 14281.018072128296, "id": 48, "iso": "IND", "lat": "77", "lon": "20", "name": "印度", "particles": 119, "polygons": [143], "polygons3D": [440], "products": {"200": 5698.59, "205": 909.652, "206": 376.162, "208": 53.737, "210": 677.988, "211": 145.091, "212": 136.135, "214": 31.347, "217": 10.747, "232": 10.747, "236": 1417.74, "247": 357.0, "249": 135.239, "250": 27.764, "253": 59.207, "260": 65.051, "262": 44.307, "263": 23.286, "266": 102.458, "268": 704.652, "269": 178.739, "270": 15.226, "273": 77.451, "278": 44.0, "280": 13.434, "284": 10.747, "291": 102.502, "891": 18.808, "981": 1504.77, "982": 1258.4, "983": 70.038}, "sub": 12}, "IR": {"area": 1648195, "continent": 2, "exports": 3242.683994293213, "id": 50, "iso": "IRN", "lat": "53", "lon": "32", "name": "伊朗", "particles": 27, "polygons": [145], "polygons3D": [442], "products": {"200": 1216.11, "205": 25.521, "206": 56.424, "208": 42.094, "210": 11.643, "236": 144.284, "249": 126.812, "250": 16.121, "253": 12.539, "266": 10.747, "268": 310.457, "269": 26.869, "270": 25.973, "273": 79.711, "291": 19.704, "981": 561.329, "982": 516.94, "983": 39.407}, "sub": 12}, "IT": {"area": 301336, "continent": 4, "exports": 157354.82806110382, "id": 52, "iso": "ITA", "lat": "12.833", "lon": "42.833333", "name": "意大利", "particles": 1311, "polygons": [149, 150, 151], "polygons3D": [446, 447, 448], "products": {"200": 57251.0, "205": 9992.01, "206": 1345.23, "208": 228.383, "209": 147.778, "210": 1177.75, "211": 309.885, "212": 51.05, "213": 293.765, "214": 332.276, "215": 43.886, "216": 133.448, "217": 46.572, "219": 58.216, "220": 42.99, "221": 15.226, "223": 154.047, "225": 106.579, "226": 46.572, "231": 11.643, "236": 14481.7, "237": 1668.55, "238": 267.791, "239": 1390.9, "240": 1424.94, "241": 16.121, "242": 242.714, "243": 1163.41, "245": 656.199, "246": 16.0, "247": 462.216, "249": 822.872, "250": 274.061, "253": 227.488, "256": 60.007, "257": 117.326, "258": 27.765, "260": 191.304, "262": 365.269, "263": 245.401, "264": 14.33, "266": 527.572, "268": 6922.68, "269": 2200.27, "271": 1657.8, "272": 194.751, "273": 3582.23, "274": 395.124, "275": 37.616, "276": 46.572, "277": 301.481, "278": 382.982, "279": 346.942, "280": 528.94, "284": 1525.44, "285": 343.024, "287": 363.606, "288": 237.34, "289": 83.293, "291": 481.855, "292": 61.798, "294": 363.623, "891": 115.535, "892": 343.92, "895": 12.539, "897": 56.425, "981": 29901.8, "982": 10415.1}, "sub": 17}, "JM": {"area": 10991, "continent": 6, "exports": 138.64799690246582, "id": 53, "iso": "JAM", "lat": "-77.5", "lon": "18.25", "name": "牙买加", "particles": 1, "polygons": [152], "polygons3D": [449], "products": {"200": 120.181, "236": 18.467}, "sub": 6}, "JO": {"area": 89342, "continent": 2, "exports": 268.1470003128052, "id": 54, "iso": "JOR", "lat": "36", "lon": "31", "name": "约旦", "particles": 2, "polygons": [153], "polygons3D": [450], "products": {"200": 148.147, "268": 30.0, "269": 30.0, "981": 30.0, "982": 30.0}, "sub": 14}, "JP": {"area": 377930, "continent": 2, "exports": 284576.55103874207, "id": 55, "iso": "JPN", "lat": "138", "lon": "36", "name": "日本", "particles": 2371, "polygons": [154, 155, 156], "polygons3D": [451, 452, 453], "products": {"200": 84211.8, "205": 19746.5, "206": 8634.71, "208": 622.458, "209": 198.829, "210": 9139.83, "211": 1445.54, "212": 329.589, "213": 284.808, "214": 209.576, "216": 56.424, "218": 84.189, "223": 81.502, "225": 55.528, "232": 33.138, "236": 19769.8, "237": 723.663, "238": 32.242, "239": 371.684, "240": 868.754, "242": 67.172, "243": 692.316, "245": 743.335, "247": 68.0, "249": 2708.8, "250": 39.407, "253": 1625.39, "257": 169.272, "260": 2027.72, "262": 1921.35, "263": 240.027, "266": 9476.86, "268": 22155.9, "269": 2304.56, "270": 264.209, "271": 111.953, "272": 80.606, "273": 3243.93, "274": 510.071, "277": 112.32, "278": 123.441, "279": 331.381, "280": 143.299, "284": 339.441, "285": 243.609, "287": 721.335, "288": 45.676, "291": 851.454, "891": 204.202, "892": 135.239, "981": 43308.8, "982": 41760.3, "983": 904.581}, "sub": 11}, "KE": {"area": 580367, "continent": 1, "exports": 147.25, "id": 57, "iso": "KEN", "lat": "38", "lon": "1", "name": "肯尼亚", "particles": 1, "polygons": [158], "polygons3D": [455], "products": {"200": 147.25}, "sub": 1}, "KG": {"area": 199951, "continent": 2, "exports": 1673846484.4450006, "id": 58, "iso": "KGZ", "lat": "75", "lon": "41", "name": "吉尔吉斯斯坦", "particles": 0, "polygons": [159], "polygons3D": [456], "products": {}, "sub": 10}, "KH": {"area": 181035, "continent": 2, "exports": 36.132999420166016, "id": 59, "iso": "KHM", "lat": "105", "lon": "13", "name": "柬埔寨", "particles": 0, "polygons": [160], "polygons3D": [457], "products": {"200": 36.133}, "sub": 13}, "KR": {"area": 100210, "continent": 2, "exports": 77224.89774513245, "id": 60, "iso": "KOR", "lat": "127.5", "lon": "37", "name": "韩国", "particles": 643, "polygons": [161], "polygons3D": [458], "products": {"200": 26825.4, "205": 7654.0, "206": 1715.12, "208": 325.111, "209": 34.034, "210": 853.529, "211": 20.599, "212": 30.451, "213": 59.111, "214": 25.973, "216": 11.643, "217": 14.33, "223": 11.643, "225": 11.643, "232": 14.33, "236": 6566.28, "245": 435.5, "247": 61.0, "249": 145.316, "250": 43.886, "253": 275.958, "260": 314.738, "262": 34.034, "263": 19.704, "266": 2273.06, "268": 6599.88, "269": 782.228, "270": 36.721, "273": 133.153, "274": 39.912, "277": 39.912, "278": 11.67, "280": 35.825, "284": 13.434, "287": 33.138, "291": 205.5, "891": 56.424, "981": 11194.1, "982": 10233.3, "983": 33.317}, "sub": 11}, "KW": {"area": 17818, "continent": 2, "exports": 375.45099925994873, "id": 61, "iso": "KWT", "lat": "47.75", "lon": "29.5", "name": "科威特", "particles": 3, "polygons": [163], "polygons3D": [460], "products": {"200": 338.451, "205": 37.0}, "sub": 14}, "KZ": {"area": 2724900, "continent": 2, "exports": 204.43000030517578, "id": 56, "iso": "KAZ", "lat": "68", "lon": "48", "name": "哈萨克斯坦", "particles": 1, "polygons": [157], "polygons3D": [454], "products": {"200": 204.43}, "sub": 10}, "LA": {"area": 236800, "continent": 2, "exports": 2127476197.8820007, "id": 62, "iso": "LAO", "lat": "105", "lon": "18", "name": "老挝", "particles": 0, "polygons": [164], "polygons3D": [461], "products": {}, "sub": 13}, "LB": {"area": 10452, "continent": 2, "exports": 331.6099901199341, "id": 63, "iso": "LBN", "lat": "35.833", "lon": "33.833333", "name": "黎巴嫩", "particles": 2, "polygons": [165], "polygons3D": [462], "products": {"200": 331.61}, "sub": 14}, "LK": {"area": 65610, "continent": 2, "exports": 262.0910015106201, "id": 66, "iso": "LKA", "lat": "81", "lon": "7", "name": "斯里兰卡", "particles": 2, "polygons": [168], "polygons3D": [465], "products": {"200": 150.091, "205": 20.0, "268": 23.0, "269": 23.0, "981": 23.0, "982": 23.0}, "sub": 12}, "LR": {"area": 111369, "continent": 1, "exports": 162.56099891662598, "id": 64, "iso": "LBR", "lat": "-9.5", "lon": "6.5", "name": "利比里亚", "particles": 1, "polygons": [166], "polygons3D": [463], "products": {"200": 145.561, "205": 17.0}, "sub": 5}, "LT": {"area": 65300, "continent": 4, "exports": 1143.7069883346558, "id": 67, "iso": "LTU", "lat": "24", "lon": "56", "name": "立陶宛", "particles": 9, "polygons": [170], "polygons3D": [467], "products": {"200": 550.929, "205": 114.307, "236": 133.402, "268": 52.378, "273": 10.615, "981": 223.901, "982": 58.175}, "sub": 16}, "LV": {"area": 64559, "continent": 4, "exports": 1303.8080043792725, "id": 68, "iso": "LVA", "lat": "25", "lon": "57", "name": "拉脱维亚", "particles": 10, "polygons": [172], "polygons3D": [469], "products": {"200": 611.489, "205": 129.25, "214": 23.286, "219": 21.495, "236": 135.36, "268": 56.622, "269": 18.0, "273": 32.061, "274": 13.422, "277": 13.017, "981": 157.542, "982": 92.264}, "sub": 16}, "LY": {"area": 1759540, "continent": 1, "exports": 654.2729902267456, "id": 65, "iso": "LBY", "lat": "17", "lon": "25", "name": "利比亚", "particles": 5, "polygons": [167], "polygons3D": [464], "products": {"200": 435.835, "205": 14.154, "236": 149.428, "268": 17.816, "981": 19.224, "982": 17.816}, "sub": 3}, "MA": {"area": 446550, "continent": 1, "exports": 3782.308985710144, "id": 69, "iso": "MAR", "lat": "-5", "lon": "32", "name": "摩洛哥", "particles": 31, "polygons": [173], "polygons3D": [470], "products": {"200": 1236.11, "205": 228.384, "206": 147.778, "208": 48.364, "210": 95.831, "214": 35.825, "236": 184.832, "245": 66.533, "249": 25.973, "250": 14.33, "253": 10.747, "262": 14.33, "268": 368.997, "291": 11.643, "981": 676.546, "982": 566.824, "983": 49.259}, "sub": 3}, "MD": {"area": 33846, "continent": 4, "exports": 147.9119987487793, "id": 70, "iso": "MDA", "lat": "29", "lon": "47", "name": "摩尔多瓦", "particles": 1, "polygons": [174], "polygons3D": [471], "products": {"200": 102.392, "205": 19.73, "236": 25.79}, "sub": 15}, "MG": {"area": 587041, "continent": 1, "exports": 154.08399963378906, "id": 71, "iso": "MDG", "lat": "47", "lon": "-20", "name": "马达加斯加", "particles": 1, "polygons": [175], "polygons3D": [472], "products": {"200": 154.084}, "sub": 1}, "MK": {"area": 25713, "continent": 4, "exports": 3703860301.268, "id": 73, "iso": "MKD", "lat": "22", "lon": "41.833333", "name": "马其顿", "particles": 0, "polygons": [177], "polygons3D": [474], "products": {}, "sub": 17}, "ML": {"area": 1240192, "continent": 1, "exports": 2894578978.072, "id": 74, "iso": "MLI", "lat": "-4", "lon": "17", "name": "马里", "particles": 0, "polygons": [178], "polygons3D": [475], "products": {}, "sub": 5}, "MN": {"area": 1564110, "continent": 2, "exports": 16.06999969482422, "id": 75, "iso": "MNG", "lat": "105", "lon": "46", "name": "蒙古", "particles": 0, "polygons": [183], "polygons3D": [480], "products": {"200": 16.07}, "sub": 11}, "MR": {"area": 1030700, "continent": 1, "exports": 35.922000885009766, "id": 77, "iso": "MRT", "lat": "-12", "lon": "20", "name": "毛里塔尼亚", "particles": 0, "polygons": [185], "polygons3D": [482], "products": {"200": 35.922}, "sub": 5}, "MU": {"area": 2040, "continent": 1, "exports": 160.5140027999878, "id": 78, "iso": "MUS", "lat": "57.583333", "lon": "-20.3", "name": "毛里求斯", "particles": 1, "products": {"200": 160.514}, "sub": 1}, "MW": {"area": 118484, "continent": 1, "exports": 983057327.2610003, "id": 79, "iso": "MWI", "lat": "34", "lon": "-13.5", "name": "马拉维", "particles": 0, "polygons": [186], "polygons3D": [483], "products": {}, "sub": 1}, "MX": {"area": 1964375, "continent": 6, "exports": 35910.1779794693, "id": 72, "iso": "MEX", "lat": "-102", "lon": "23", "name": "墨西哥", "particles": 299, "polygons": [176], "polygons3D": [473], "products": {"200": 16337.2, "205": 2276.91, "206": 447.812, "208": 86.875, "210": 286.6, "211": 109.266, "214": 92.249, "236": 8577.78, "247": 746.0, "249": 333.173, "250": 15.226, "253": 227.267, "257": 105.684, "260": 33.138, "262": 46.572, "263": 46.572, "266": 369.461, "268": 632.503, "269": 79.902, "270": 54.633, "273": 245.401, "274": 16.121, "277": 15.226, "279": 120.909, "280": 36.721, "284": 60.007, "287": 14.33, "291": 201.0, "891": 91.354, "981": 2449.73, "982": 1743.51, "983": 11.106}, "sub": 7}, "MY": {"area": 330803, "continent": 2, "exports": 12573.400966644287, "id": 80, "iso": "MYS", "lat": "112.5", "lon": "2.5", "name": "马来西亚", "particles": 104, "polygons": [187, 188], "polygons3D": [484, 485], "products": {"200": 5091.56, "205": 1135.61, "206": 555.286, "208": 40.303, "210": 289.287, "211": 11.643, "212": 50.155, "213": 10.747, "236": 967.823, "245": 19.704, "247": 10.0, "249": 217.637, "250": 60.007, "253": 52.842, "257": 17.017, "260": 51.512, "262": 28.912, "263": 17.912, "266": 266.191, "268": 583.942, "269": 109.539, "273": 75.259, "274": 19.0, "277": 19.0, "280": 19.704, "284": 10.747, "285": 11.643, "287": 12.539, "291": 12.539, "981": 1472.03, "982": 1318.53, "983": 14.778}, "sub": 13}, "MZ": {"area": 801590, "continent": 1, "exports": 73.68399906158447, "id": 76, "iso": "MOZ", "lat": "35", "lon": "-18.25", "name": "莫桑比克", "particles": 0, "polygons": [184], "polygons3D": [481], "products": {"200": 73.684}, "sub": 1}, "NG": {"area": 923768, "continent": 1, "exports": 3054.646007537842, "id": 81, "iso": "NGA", "lat": "8", "lon": "10", "name": "尼日利亚", "particles": 25, "polygons": [192], "polygons3D": [489], "products": {"200": 1122.0, "205": 217.724, "206": 255.253, "208": 55.529, "210": 25.077, "211": 24.182, "249": 244.505, "250": 244.505, "268": 76.276, "269": 29.704, "270": 19.704, "273": 46.677, "280": 30.451, "284": 15.226, "981": 326.155, "982": 321.677}, "sub": 5}, "NI": {"area": 130373, "continent": 6, "exports": 34.0310001373291, "id": 82, "iso": "NIC", "lat": "-85", "lon": "13", "name": "尼加拉瓜", "particles": 0, "polygons": [193], "polygons3D": [490], "products": {"200": 34.031}, "sub": 7}, "NL": {"area": 41850, "continent": 4, "exports": 146829.89009666443, "id": 83, "iso": "NLD", "lat": "5.75", "lon": "52.5", "name": "荷兰", "particles": 1223, "polygons": [194], "polygons3D": [491], "products": {"200": 51121.1, "205": 8747.07, "206": 2226.52, "208": 978.021, "209": 117.326, "210": 757.699, "211": 248.984, "212": 15.226, "213": 151.36, "214": 476.47, "216": 278.538, "217": 51.946, "223": 312.573, "225": 256.149, "226": 51.946, "236": 11877.4, "237": 508.714, "240": 1621.97, "245": 650.195, "246": 200.841, "247": 345.932, "249": 460.941, "250": 41.199, "253": 658.484, "255": 317.05, "260": 374.155, "262": 994.001, "263": 560.66, "266": 1753.2, "268": 7731.95, "269": 917.382, "272": 330.518, "273": 4101.08, "274": 1535.32, "277": 414.0, "278": 168.364, "279": 187.0, "280": 1188.93, "284": 51.0, "285": 936.822, "287": 379.63, "288": 82.397, "289": 74.337, "291": 160.684, "892": 1202.82, "981": 27839.1, "982": 13373.0}, "sub": 18}, "NO": {"area": 323802, "continent": 4, "exports": 46832.291127204895, "id": 84, "iso": "NOR", "lat": "10", "lon": "62", "name": "挪威", "particles": 390, "polygons": [195, 196, 197, 198], "polygons3D": [492, 493, 494, 495], "products": {"200": 16065.2, "205": 3069.56, "206": 2042.02, "207": 12.539, "208": 364.518, "209": 39.407, "210": 802.48, "211": 287.495, "212": 11.643, "214": 352.875, "216": 15.226, "219": 12.539, "223": 154.943, "225": 13.434, "236": 4940.97, "237": 21.495, "240": 62.694, "243": 26.869, "245": 112.849, "247": 101.189, "249": 617.98, "250": 468.411, "253": 292.867, "257": 20.599, "260": 234.117, "262": 493.488, "263": 36.72, "266": 239.131, "268": 3142.73, "269": 299.91, "270": 60.902, "272": 83.293, "273": 401.5, "274": 17.017, "277": 12.539, "280": 13.434, "284": 20.599, "285": 11.643, "287": 137.926, "288": 13.434, "291": 47.964, "981": 5834.47, "982": 5457.31, "983": 364.339}, "sub": 16}, "NZ": {"area": 270467, "continent": 3, "exports": 9757.98600101471, "id": 85, "iso": "NZL", "lat": "174", "lon": "-42", "name": "新西兰", "particles": 81, "polygons": [200, 201], "polygons3D": [497, 498], "products": {"200": 3953.41, "205": 936.563, "206": 248.088, "208": 42.094, "210": 169.273, "211": 40.303, "213": 47.468, "236": 1460.48, "245": 67.313, "253": 75.525, "260": 43.637, "262": 74.74, "266": 262.75, "268": 307.637, "273": 21.143, "278": 10.352, "287": 24.14, "981": 1012.79, "982": 960.28}, "sub": 19}, "OM": {"area": 309500, "continent": 2, "exports": 87.91299819946289, "id": 86, "iso": "OMN", "lat": "57", "lon": "21", "name": "阿曼", "particles": 0, "polygons": [202, 203], "polygons3D": [499, 500], "products": {"200": 87.913}, "sub": 14}, "PA": {"area": 75417, "continent": 5, "exports": 429.136999130249, "id": 88, "iso": "PAN", "lat": "-80", "lon": "9", "name": "巴拿马", "particles": 3, "polygons": [205], "polygons3D": [502], "products": {"200": 369.137, "205": 38.0, "981": 11.0, "982": 11.0}, "sub": 7}, "PE": {"area": 1285216, "continent": 5, "exports": 126.47900009155273, "id": 89, "iso": "PER", "lat": "-76", "lon": "-10", "name": "秘鲁", "particles": 1, "polygons": [206], "polygons3D": [503], "products": {"200": 126.479}, "sub": 8}, "PG": {"area": 462840, "continent": 3, "exports": 424.1499881744385, "id": 91, "iso": "PNG", "lat": "147", "lon": "-6", "name": "巴布亚新几内亚", "particles": 3, "polygons": [214, 215, 216, 217], "polygons3D": [511, 512, 513, 514], "products": {"200": 185.954, "236": 51.836, "268": 23.626, "291": 51.655, "981": 81.367, "982": 29.712}, "sub": 20}, "PH": {"area": 342353, "continent": 2, "exports": 8298.081018447876, "id": 90, "iso": "PHL", "lat": "122", "lon": "13", "name": "菲律宾", "particles": 69, "polygons": [207, 208, 209, 210, 211, 212, 213], "polygons3D": [504, 505, 506, 507, 508, 509, 510], "products": {"200": 3392.43, "205": 741.832, "206": 214.95, "210": 213.158, "211": 21.495, "212": 11.643, "214": 27.764, "217": 25.973, "232": 25.973, "236": 986.655, "245": 16.121, "247": 171.0, "249": 141.509, "253": 33.138, "260": 10.0, "262": 11.0, "266": 120.013, "268": 350.121, "269": 102.034, "270": 34.034, "273": 25.077, "291": 10.738, "891": 10.747, "981": 818.566, "982": 782.109}, "sub": 13}, "PK": {"area": 881912, "continent": 2, "exports": 746.6780004501343, "id": 87, "iso": "PAK", "lat": "70", "lon": "30", "name": "巴基斯坦", "particles": 6, "polygons": [204], "polygons3D": [501], "products": {"200": 564.395, "205": 13.0, "236": 15.283, "268": 38.0, "269": 38.0, "981": 39.0, "982": 39.0}, "sub": 12}, "PL": {"area": 312679, "continent": 4, "exports": 11902.168969154358, "id": 92, "iso": "POL", "lat": "20", "lon": "52", "name": "波兰", "particles": 99, "polygons": [218], "polygons3D": [515], "products": {"200": 4906.55, "205": 849.155, "236": 1582.77, "245": 73.0, "247": 70.0, "249": 357.519, "262": 29.0, "268": 403.088, "269": 53.0, "272": 20.0, "273": 200.742, "274": 66.0, "277": 66.0, "278": 48.409, "279": 15.0, "280": 54.0, "284": 11.0, "291": 16.0, "981": 2172.56, "982": 908.374}, "sub": 15}, "PT": {"area": 92090, "continent": 4, "exports": 16344.331999778748, "id": 93, "iso": "PRT", "lat": "-8", "lon": "39.5", "name": "葡萄牙", "particles": 136, "polygons": [221], "polygons3D": [518], "products": {"200": 6465.56, "205": 1801.99, "236": 1759.9, "245": 37.747, "247": 22.0, "249": 38.0, "253": 12.539, "260": 29.434, "262": 44.781, "266": 111.057, "268": 647.165, "269": 24.0, "273": 61.0, "274": 16.0, "277": 16.0, "279": 19.0, "280": 14.0, "287": 73.441, "291": 25.973, "981": 2498.88, "982": 1047.78, "983": 1578.09}, "sub": 17}, "PY": {"area": 406752, "continent": 5, "exports": 5186996500.509997, "id": 94, "iso": "PRY", "lat": "-57.96871", "lon": "-22.993333", "name": "巴拉圭", "particles": 0, "polygons": [222], "polygons3D": [519], "products": {}, "sub": 8}, "QA": {"area": 11586, "continent": 2, "exports": 350.2320022583008, "id": 95, "iso": "QAT", "lat": "51.25", "lon": "25.5", "name": "卡塔尔", "particles": 2, "polygons": [223], "polygons3D": [520], "products": {"200": 350.232}, "sub": 14}, "RO": {"area": 238391, "continent": 4, "exports": 2657.1750164031982, "id": 96, "iso": "ROU", "lat": "25", "lon": "46", "name": "罗马尼亚", "particles": 22, "polygons": [224], "polygons3D": [521], "products": {"200": 941.394, "205": 135.239, "206": 19.704, "210": 41.199, "211": 12.539, "214": 53.738, "216": 11.643, "223": 11.643, "225": 11.643, "236": 243.721, "245": 16.94, "249": 34.929, "250": 14.33, "260": 16.94, "268": 194.501, "269": 10.747, "270": 10.747, "273": 27.738, "981": 477.94, "982": 369.9}, "sub": 15}, "RU": {"area": 17098242, "continent": 2, "exports": 50423.00796222687, "id": 97, "iso": "RUS", "lat": "100", "lon": "60", "name": "俄国", "particles": 420, "polygons": [225, 226, 227, 228, 229, 230, 231, 232, 233, 234, 235, 236, 237], "polygons3D": [522, 523, 524, 525, 526, 527, 528, 529, 530, 531, 532, 533, 534], "products": {"200": 14947.8, "205": 672.941, "206": 334.964, "208": 167.482, "210": 236.444, "211": 15.226, "213": 25.973, "214": 856.216, "216": 52.842, "219": 54.633, "223": 80.607, "225": 51.051, "231": 485.428, "236": 7739.85, "237": 158.525, "240": 323.32, "243": 97.623, "245": 289.811, "247": 14.33, "249": 1280.62, "250": 169.273, "253": 159.857, "257": 29.556, "260": 103.024, "262": 229.414, "263": 34.929, "264": 11.05, "266": 284.045, "268": 2828.42, "269": 378.233, "270": 276.748, "271": 17.017, "272": 128.403, "273": 2261.8, "274": 613.898, "275": 86.963, "276": 56.438, "277": 444.129, "278": 440.708, "279": 49.941, "280": 496.401, "284": 431.339, "287": 130.104, "294": 12.539, "981": 6124.57, "982": 5630.92, "983": 1107.62}, "sub": 15}, "SA": {"area": 2149690, "continent": 2, "exports": 5481.440967559814, "id": 98, "iso": "SAU", "lat": "45", "lon": "25", "name": "沙特阿拉伯", "particles": 45, "polygons": [240], "polygons3D": [537], "products": {"200": 3300.41, "205": 265.182, "236": 254.287, "247": 37.0, "249": 329.378, "253": 11.963, "266": 11.963, "268": 188.216, "981": 541.519, "982": 541.519}, "sub": 14}, "SE": {"area": 450295, "continent": 4, "exports": 63554.47813796997, "id": 104, "iso": "SWE", "lat": "15", "lon": "62", "name": "瑞典", "particles": 529, "polygons": [257, 258, 259, 260], "polygons3D": [554, 555, 556, 557], "products": {"200": 21407.4, "205": 2486.01, "206": 384.221, "208": 189.871, "209": 151.36, "210": 102.101, "211": 42.095, "213": 49.259, "214": 138.821, "217": 39.407, "223": 134.343, "226": 39.407, "236": 5681.08, "245": 254.707, "246": 35.704, "247": 206.009, "249": 225.205, "250": 14.33, "251": 26.868, "253": 91.64, "256": 13.434, "260": 142.607, "262": 321.03, "263": 91.353, "264": 45.677, "266": 430.335, "268": 4646.39, "269": 265.556, "271": 54.633, "272": 104.391, "273": 3638.24, "274": 409.386, "275": 94.04, "276": 186.289, "277": 120.0, "278": 306.852, "279": 1092.52, "280": 746.447, "284": 344.815, "287": 54.107, "291": 26.344, "981": 12234.9, "982": 6485.35}, "sub": 16}, "SG": {"area": 710, "continent": 2, "exports": 58583.49937915802, "id": 100, "iso": "SGP", "lat": "103.8", "lon": "1.366667", "name": "新加坡", "particles": 488, "products": {"200": 19182.4, "205": 2716.97, "206": 1710.64, "208": 151.36, "210": 784.566, "211": 61.798, "212": 23.286, "213": 77.024, "236": 1428.62, "245": 44.66, "247": 18.0, "249": 285.702, "250": 12.539, "253": 466.101, "260": 494.6, "262": 175.341, "263": 33.138, "266": 3041.07, "268": 4737.02, "269": 929.404, "270": 191.663, "273": 291.482, "274": 82.912, "277": 79.121, "278": 57.0, "280": 17.912, "284": 19.704, "285": 76.128, "287": 106.541, "291": 188.585, "891": 17.912, "981": 11510.3, "982": 9506.61, "983": 63.32}, "sub": 13}, "SI": {"area": 20273, "continent": 4, "exports": 3986.1849794387817, "id": 103, "iso": "SVN", "lat": "15.166667", "lon": "46.25", "name": "斯洛文尼亚", "particles": 33, "polygons": [256], "polygons3D": [553], "products": {"200": 1462.05, "205": 213.159, "214": 18.808, "216": 15.226, "236": 486.179, "240": 254.357, "243": 246.297, "245": 17.912, "247": 17.017, "249": 36.599, "262": 12.0, "266": 24.182, "268": 151.898, "269": 11.0, "273": 83.259, "274": 10.0, "277": 10.0, "280": 13.0, "892": 24.182, "981": 575.887, "982": 303.174}, "sub": 17}, "SK": {"area": 49037, "continent": 4, "exports": 6229.897034645081, "id": 102, "iso": "SVK", "lat": "19.5", "lon": "48.666667", "name": "斯洛伐克", "particles": 51, "polygons": [255], "polygons3D": [552], "products": {"200": 2364.4, "205": 122.7, "210": 15.226, "211": 14.33, "214": 233.758, "219": 169.274, "223": 25.973, "232": 25.077, "236": 377.953, "245": 10.747, "249": 63.182, "260": 51.051, "262": 17.017, "266": 10.747, "268": 471.793, "269": 177.108, "273": 190.761, "274": 10.0, "277": 10.0, "280": 34.058, "981": 1101.34, "982": 733.406}, "sub": 15}, "SN": {"area": 196722, "continent": 1, "exports": 339.4900007247925, "id": 99, "iso": "SEN", "lat": "-14", "lon": "14", "name": "塞内加尔", "particles": 2, "polygons": [243], "polygons3D": [540], "products": {"200": 339.49}, "sub": 5}, "SV": {"area": 21041, "continent": 6, "exports": 5492290585.256005, "id": 101, "iso": "SLV", "lat": "-88.9123", "lon": "13.833333", "name": "萨尔瓦多", "particles": 0, "polygons": [250], "polygons3D": [547], "products": {}, "sub": 7}, "SY": {"area": 185180, "continent": 2, "exports": 143.5699977874756, "id": 105, "iso": "SYR", "lat": "38", "lon": "35", "name": "叙利亚", "particles": 1, "polygons": [262], "polygons3D": [559], "products": {"200": 143.57}, "sub": 14}, "TH": {"area": 513120, "continent": 2, "exports": 13973.454159736633, "id": 106, "iso": "THA", "lat": "100", "lon": "15", "name": "泰国", "particles": 116, "polygons": [265], "polygons3D": [562], "products": {"200": 5312.05, "205": 1251.29, "206": 444.229, "208": 18.808, "210": 500.654, "211": 39.407, "212": 30.451, "213": 25.077, "214": 13.434, "236": 1165.13, "247": 27.0, "249": 330.485, "250": 24.182, "253": 25.973, "260": 36.182, "262": 19.704, "263": 19.704, "266": 485.428, "268": 624.314, "269": 109.912, "270": 17.017, "273": 69.32, "285": 34.929, "291": 18.808, "891": 31.347, "981": 1680.0, "982": 1618.61}, "sub": 13}, "TJ": {"area": 143100, "continent": 2, "exports": 846230171.2709999, "id": 107, "iso": "TJK", "lat": "71", "lon": "39", "name": "塔吉克斯坦", "particles": 0, "polygons": [266], "polygons3D": [563], "products": {}, "sub": 10}, "TM": {"area": 488100, "continent": 2, "exports": 87.91300201416016, "id": 108, "iso": "TKM", "lat": "60", "lon": "40", "name": "土库曼斯坦", "particles": 0, "polygons": [267], "polygons3D": [564], "products": {"200": 87.913}, "sub": 10}, "TN": {"area": 163610, "continent": 1, "exports": 2335.7769813537598, "id": 110, "iso": "TUN", "lat": "9", "lon": "34", "name": "突尼斯", "particles": 19, "polygons": [270], "polygons3D": [567], "products": {"200": 1104.94, "205": 367.795, "236": 155.695, "268": 209.212, "291": 37.604, "981": 251.323, "982": 209.212}, "sub": 3}, "TR": {"area": 783562, "continent": 2, "exports": 19491.792031288147, "id": 111, "iso": "TUR", "lat": "34.911", "lon": "39.059012", "name": "土耳其", "particles": 162, "polygons": [271, 272], "polygons3D": [568, 569], "products": {"200": 7937.29, "205": 353.418, "206": 201.515, "208": 34.929, "210": 342.128, "211": 56.424, "212": 28.66, "213": 109.266, "214": 54.633, "216": 16.121, "223": 15.226, "225": 15.226, "236": 5967.04, "245": 35.476, "249": 143.138, "250": 42.99, "253": 38.512, "260": 114.103, "262": 13.434, "263": 13.434, "266": 13.434, "268": 766.135, "269": 85.145, "270": 31.347, "273": 85.481, "280": 16.121, "284": 35.825, "291": 25.669, "294": 13.434, "891": 12.539, "981": 1436.73, "982": 1277.28, "983": 159.69}, "sub": 14}, "TT": {"area": 5130, "continent": 6, "exports": 138.0870018005371, "id": 109, "iso": "TTO", "lat": "-61", "lon": "11", "name": "特立尼达和多巴哥", "particles": 1, "polygons": [269], "polygons3D": [566], "products": {"200": 113.253, "236": 24.834}, "sub": 6}, "TZ": {"area": 945087, "continent": 1, "exports": 72.64299869537354, "id": 112, "iso": "TZA", "lat": "35", "lon": "-6", "name": "坦桑尼亚", "particles": 0, "polygons": [274], "polygons3D": [571], "products": {"200": 72.643}, "sub": 1}, "UA": {"area": 603500, "continent": 4, "exports": 1106.0329999923706, "id": 114, "iso": "UKR", "lat": "32", "lon": "49", "name": "乌克兰", "particles": 9, "polygons": [276], "polygons3D": [573], "products": {"200": 695.153, "205": 101.784, "236": 65.031, "268": 77.024, "981": 84.416, "982": 82.625}, "sub": 15}, "UG": {"area": 241550, "continent": 1, "exports": 11.343999862670898, "id": 113, "iso": "UGA", "lat": "33", "lon": "2", "name": "乌干达", "particles": 0, "polygons": [275], "polygons3D": [572], "products": {"200": 11.344}, "sub": 1}, "US": {"area": 9372610, "continent": 6, "exports": 871755.7492666245, "id": 116, "iso": "USA", "lat": "-98.57", "lon": "39.828175", "name": "美国", "particles": 7264, "polygons": [278, 279, 280, 281, 282, 283, 284, 285, 286, 287], "polygons3D": [575, 576, 577, 578, 579, 580, 581, 582, 583, 584], "products": {"200": 256462.0, "205": 36423.8, "206": 13507.8, "207": 157.63, "208": 4532.75, "209": 690.526, "210": 7961.2, "211": 4737.85, "212": 869.651, "213": 853.531, "214": 1779.6, "215": 128.97, "216": 577.677, "217": 240.027, "218": 251.67, "219": 223.011, "220": 161.213, "221": 25.077, "223": 566.93, "225": 531.105, "226": 26.869, "227": 21.494, "229": 10.747, "231": 137.03, "232": 355.562, "236": 62596.0, "237": 1184.91, "238": 71.65, "239": 679.779, "240": 3282.46, "242": 224.801, "243": 2241.75, "245": 3139.5, "246": 393.179, "247": 3154.47, "249": 1829.26, "250": 710.23, "251": 81.501, "253": 3830.59, "255": 95.831, "256": 481.846, "257": 4830.99, "258": 34.034, "260": 10243.7, "262": 5526.92, "263": 1862.0, "264": 268.416, "266": 35640.6, "268": 54293.0, "269": 10581.2, "270": 3920.14, "271": 1100.72, "272": 723.832, "273": 30725.9, "274": 7064.83, "275": 297.937, "276": 108.37, "277": 3408.0, "278": 2558.82, "279": 4659.44, "280": 2373.72, "282": 168.11, "284": 4326.62, "285": 2887.49, "287": 2909.51, "288": 731.724, "289": 285.704, "291": 4886.23, "292": 63.589, "293": 3552.04, "294": 39.407, "891": 918.91, "892": 709.334, "895": 81.502, "896": 41.199, "897": 51.946, "958": 31.347, "959": 68.067, "981": 133334.0, "982": 117635.0, "983": 3579.09}, "sub": 9}, "UY": {"area": 181034, "continent": 5, "exports": 670.3689947128296, "id": 115, "iso": "URY", "lat": "-56", "lon": "-33", "name": "乌拉圭", "particles": 5, "polygons": [277], "polygons3D": [574], "products": {"200": 209.246, "205": 30.598, "206": 12.539, "268": 121.278, "981": 162.436, "982": 134.272}, "sub": 8}, "UZ": {"area": 447400, "continent": 2, "exports": 33.02699947357178, "id": 117, "iso": "UZB", "lat": "63.849", "lon": "41.707542", "name": "乌兹别克斯坦", "particles": 0, "polygons": [288], "polygons3D": [585], "products": {"200": 33.027}, "sub": 10}, "VE": {"area": 916445, "continent": 5, "exports": 3156.801010131836, "id": 118, "iso": "VEN", "lat": "-66", "lon": "8", "name": "委内瑞拉", "particles": 26, "polygons": [289], "polygons3D": [586], "products": {"200": 1343.96, "205": 267.936, "206": 99.414, "208": 14.33, "210": 39.407, "211": 15.226, "236": 255.983, "247": 30.0, "249": 41.199, "250": 15.226, "253": 38.512, "262": 10.747, "263": 10.747, "266": 48.363, "268": 109.266, "291": 26.0, "891": 25.077, "981": 446.57, "982": 293.764, "983": 25.077}, "sub": 8}, "VN": {"area": 331212, "continent": 2, "exports": 1921.3679819107056, "id": 119, "iso": "VNM", "lat": "107.8358", "lon": "16.166667", "name": "越南", "particles": 16, "polygons": [290], "polygons3D": [587], "products": {"200": 940.142, "205": 102.936, "236": 216.298, "249": 53.434, "268": 127.823, "269": 27.0, "273": 17.593, "280": 16.39, "981": 218.181, "982": 201.571}, "sub": 13}, "YE": {"area": 527968, "continent": 2, "exports": 68.06199645996094, "id": 120, "iso": "YEM", "lat": "47.5", "lon": "15.5", "name": "也门", "particles": 0, "polygons": [294], "polygons3D": [591], "products": {"200": 68.062}, "sub": 14}, "ZA": {"area": 1221037, "continent": 1, "exports": 13582.424885749817, "id": 121, "iso": "ZAF", "lat": "26", "lon": "-30", "name": "南非", "particles": 113, "polygons": [295, 296], "polygons3D": [592, 593], "products": {"200": 4604.33, "205": 581.262, "206": 337.651, "208": 85.084, "210": 430.795, "211": 62.694, "212": 46.572, "213": 57.32, "214": 25.973, "236": 825.867, "247": 17.0, "249": 67.393, "250": 13.434, "253": 277.644, "257": 48.364, "260": 189.945, "262": 192.559, "263": 49.259, "266": 114.64, "268": 908.894, "269": 116.596, "270": 11.643, "273": 148.725, "280": 29.556, "284": 87.823, "285": 22.391, "287": 35.825, "291": 65.017, "891": 64.485, "981": 2107.68, "982": 1880.42, "983": 75.591}, "sub": 4}, "ZM": {"area": 752612, "continent": 1, "exports": 40.64799880981445, "id": 122, "iso": "ZMB", "lat": "30", "lon": "-15", "name": "赞比亚", "particles": 0, "polygons": [297], "polygons3D": [594], "products": {"200": 40.648}, "sub": 1}, "ZW": {"area": 390757, "continent": 1, "exports": 3552233277.6870003, "id": 123, "iso": "ZWE", "lat": "29", "lon": "-19", "name": "津巴布韦", "particles": 0, "polygons": [298], "polygons3D": [595], "products": {}, "sub": 1}}, "products": {"200": {"atlasid": "200", "color": "#ffff00", "id": 587, "name": "总EBOPS服务", "sales": 1321640.0, "x": 0, "y": 0}, "205": {"atlasid": "205", "color": "#FFE999", "id": 500, "name": " 运输", "sales": 222797.0, "x": 0, "y": 0}, "206": {"atlasid": "206", "color": "#FFE999", "id": 501, "name": "海运", "sales": 57923.6, "x": 0, "y": 0}, "207": {"atlasid": "207", "color": "#FFE999", "id": 502, "name": "乘客", "sales": 243.61, "x": 0, "y": 0}, "208": {"atlasid": "208", "color": "#FFE999", "id": 503, "name": "货物", "sales": 14690.0, "x": 0, "y": 0}, "209": {"atlasid": "209", "color": "#FFE999", "id": 504, "name": "其他", "sales": 4438.71, "x": 0, "y": 0}, "210": {"atlasid": "210", "color": "#FFE999", "id": 505, "name": "航空运输", "sales": 43952.7, "x": 0, "y": 0}, "211": {"atlasid": "211", "color": "#FFE999", "id": 506, "name": "乘客", "sales": 13828.4, "x": 0, "y": 0}, "212": {"atlasid": "212", "color": "#FFE999", "id": 507, "name": "货物", "sales": 2986.9, "x": 0, "y": 0}, "213": {"atlasid": "213", "color": "#FFE999", "id": 508, "name": "其他", "sales": 6071.43, "x": 0, "y": 0}, "214": {"atlasid": "214", "color": "#FFE999", "id": 509, "name": "其他运输", "sales": 9842.9, "x": 0, "y": 0}, "215": {"atlasid": "215", "color": "#FFE999", "id": 510, "name": "乘客", "sales": 399.448, "x": 0, "y": 0}, "216": {"atlasid": "216", "color": "#FFE999", "id": 511, "name": "货物", "sales": 2087.7, "x": 0, "y": 0}, "217": {"atlasid": "217", "color": "#FFE999", "id": 512, "name": "其他", "sales": 1862.0, "x": 0, "y": 0}, "218": {"atlasid": "218", "color": "#FFE999", "id": 513, "name": "其他运输", "sales": 506.923, "x": 0, "y": 0}, "219": {"atlasid": "219", "color": "#FFE999", "id": 514, "name": "其他运输", "sales": 1191.18, "x": 0, "y": 0}, "220": {"atlasid": "220", "color": "#FFE999", "id": 515, "name": "乘客", "sales": 456.769, "x": 0, "y": 0}, "221": {"atlasid": "221", "color": "#FFE999", "id": 516, "name": "货物", "sales": 138.822, "x": 0, "y": 0}, "222": {"atlasid": "222", "color": "#FFE999", "id": 517, "name": "其他", "sales": 40.303, "x": 0, "y": 0}, "223": {"atlasid": "223", "color": "#FFE999", "id": 518, "name": "其他运输", "sales": 2514.91, "x": 0, "y": 0}, "225": {"atlasid": "225", "color": "#FFE999", "id": 520, "name": "货物", "sales": 1641.68, "x": 0, "y": 0}, "226": {"atlasid": "226", "color": "#FFE999", "id": 521, "name": "其他", "sales": 285.703, "x": 0, "y": 0}, "227": {"atlasid": "227", "color": "#FFE999", "id": 522, "name": "其他运输", "sales": 58.215, "x": 0, "y": 0}, "229": {"atlasid": "229", "color": "#FFE999", "id": 524, "name": "货物", "sales": 47.468, "x": 0, "y": 0}, "231": {"atlasid": "231", "color": "#FFE999", "id": 526, "name": "其他运输", "sales": 757.696, "x": 0, "y": 0}, "232": {"atlasid": "232", "color": "#FFE999", "id": 527, "name": "其他运输", "sales": 1872.74, "x": 0, "y": 0}, "236": {"atlasid": "236", "color": "#FFC41C", "id": 528, "name": "旅行", "sales": 350590.0, "x": 0, "y": 0}, "237": {"atlasid": "237", "color": "#FFC41C", "id": 529, "name": "商务旅行", "sales": 6567.61, "x": 0, "y": 0}, "238": {"atlasid": "238", "color": "#FFC41C", "id": 530, "name": "季节性和边境工人的支出", "sales": 512.295, "x": 0, "y": 0}, "239": {"atlasid": "239", "color": "#FFC41C", "id": 531, "name": "其他", "sales": 4154.8, "x": 0, "y": 0}, "240": {"atlasid": "240", "color": "#FFC41C", "id": 532, "name": "个人旅行", "sales": 19142.2, "x": 0, "y": 0}, "241": {"atlasid": "241", "color": "#FFC41C", "id": 533, "name": "与健康有关的支出", "sales": 84.188, "x": 0, "y": 0}, "242": {"atlasid": "242", "color": "#FFC41C", "id": 534, "name": "与教育有关的支出", "sales": 916.222, "x": 0, "y": 0}, "243": {"atlasid": "243", "color": "#FFC41C", "id": 535, "name": "其他", "sales": 14774.2, "x": 0, "y": 0}, "245": {"atlasid": "245", "color": "#D1FF00", "id": 536, "name": "通讯服务", "sales": 15322.9, "x": 0, "y": 0}, "246": {"atlasid": "246", "color": "#D1FF00", "id": 537, "name": "邮政和快递服务", "sales": 1487.89, "x": 0, "y": 0}, "247": {"atlasid": "247", "color": "#D1FF00", "id": 538, "name": "电信服务", "sales": 10866.3, "x": 0, "y": 0}, "249": {"atlasid": "249", "color": "#8a6d6d", "id": 541, "name": "建筑服务", "sales": 19449.1, "x": 0, "y": 0}, "250": {"atlasid": "250", "color": "#8a6d6d", "id": 542, "name": "国外建设", "sales": 3927.31, "x": 0, "y": 0}, "251": {"atlasid": "251", "color": "#8a6d6d", "id": 543, "name": "编制经济中的建设", "sales": 212.261, "x": 0, "y": 0}, "253": {"atlasid": "253", "color": "#e377c2", "id": 544, "name": "保险服务", "sales": 22207.1, "x": 0, "y": 0}, "254": {"atlasid": "254", "color": "#e377c2", "id": 545, "name": "人寿保险和养老基金", "sales": 154.047, "x": 0, "y": 0}, "255": {"atlasid": "255", "color": "#e377c2", "id": 546, "name": "运费保险", "sales": 495.278, "x": 0, "y": 0}, "256": {"atlasid": "256", "color": "#e377c2", "id": 547, "name": "其他直接保险", "sales": 950.256, "x": 0, "y": 0}, "257": {"atlasid": "257", "color": "#e377c2", "id": 548, "name": "再保险", "sales": 6768.23, "x": 0, "y": 0}, "258": {"atlasid": "258", "color": "#e377c2", "id": 549, "name": "辅助服务", "sales": 61.799, "x": 0, "y": 0}, "260": {"atlasid": "260", "color": "#ff0000", "id": 550, "name": "金融服务", "sales": 31757.5, "x": 0, "y": 0}, "262": {"atlasid": "262", "color": "#f7b6d2", "id": 551, "name": "计算机和信息服务", "sales": 24013.3, "x": 0, "y": 0}, "263": {"atlasid": "263", "color": "#f7b6d2", "id": 552, "name": "电脑服务", "sales": 7900.29, "x": 0, "y": 0}, "264": {"atlasid": "264", "color": "#f7b6d2", "id": 553, "name": "信息服务", "sales": 834.665, "x": 0, "y": 0}, "266": {"atlasid": "266", "color": "#98df8a", "id": 556, "name": "特许权使用费和许可费", "sales": 83443.7, "x": 0, "y": 0}, "268": {"atlasid": "268", "color": "#9edae5", "id": 559, "name": "其他商业服务", "sales": 231339.0, "x": 0, "y": 0}, "269": {"atlasid": "269", "color": "#9edae5", "id": 560, "name": "招商及其他与贸易有关的服务", "sales": 41729.8, "x": 0, "y": 0}, "270": {"atlasid": "270", "color": "#9edae5", "id": 561, "name": "商贸服务", "sales": 6199.51, "x": 0, "y": 0}, "271": {"atlasid": "271", "color": "#9edae5", "id": 562, "name": "其他与贸易有关的服务", "sales": 6613.28, "x": 0, "y": 0}, "272": {"atlasid": "272", "color": "#9edae5", "id": 563, "name": "经营租赁服务", "sales": 4575.08, "x": 0, "y": 0}, "273": {"atlasid": "273", "color": "#9edae5", "id": 564, "name": "杂项业务,专业和技术服务", "sales": 109291.0, "x": 0, "y": 0}, "274": {"atlasid": "274", "color": "#9edae5", "id": 565, "name": "法律,会计,管理咨询和公共关系", "sales": 26733.9, "x": 0, "y": 0}, "275": {"atlasid": "275", "color": "#9edae5", "id": 566, "name": "法律服务", "sales": 895.745, "x": 0, "y": 0}, "276": {"atlasid": "276", "color": "#9edae5", "id": 567, "name": "会计,审计,簿记和税务咨询服务", "sales": 518.895, "x": 0, "y": 0}, "277": {"atlasid": "277", "color": "#9edae5", "id": 568, "name": "商业和管理咨询和公共关系服务", "sales": 17400.0, "x": 0, "y": 0}, "278": {"atlasid": "278", "color": "#9edae5", "id": 569, "name": "广告,市场调查和民意调查", "sales": 12001.8, "x": 0, "y": 0}, "279": {"atlasid": "279", "color": "#9edae5", "id": 570, "name": "研究与开发", "sales": 16334.3, "x": 0, "y": 0}, "280": {"atlasid": "280", "color": "#9edae5", "id": 571, "name": "建筑,工程和其他技术服务", "sales": 14119.2, "x": 0, "y": 0}, "281": {"atlasid": "281", "color": "#9edae5", "id": 572, "name": "农业,采矿和现场加工服务", "sales": 80.606, "x": 0, "y": 0}, "282": {"atlasid": "282", "color": "#9edae5", "id": 573, "name": "废物处理和去污", "sales": 322.848, "x": 0, "y": 0}, "283": {"atlasid": "283", "color": "#9edae5", "id": 574, "name": "农业,采矿和其他现场加工服务", "sales": 76.128, "x": 0, "y": 0}, "284": {"atlasid": "284", "color": "#9edae5", "id": 575, "name": "其他商业服务", "sales": 14847.5, "x": 0, "y": 0}, "285": {"atlasid": "285", "color": "#9edae5", "id": 576, "name": "相关企业之间的服务,聂", "sales": 9681.69, "x": 0, "y": 0}, "287": {"atlasid": "287", "color": "#0000ff", "id": 577, "name": "个人,文化和娱乐服务", "sales": 11584.7, "x": 0, "y": 0}, "288": {"atlasid": "288", "color": "#0000ff", "id": 578, "name": "视听和相关服务", "sales": 3532.34, "x": 0, "y": 0}, "289": {"atlasid": "289", "color": "#0000ff", "id": 579, "name": "其他个人,文化和娱乐服务", "sales": 709.334, "x": 0, "y": 0}, "291": {"atlasid": "291", "color": "#3ab11a", "id": 583, "name": "政府服务,聂", "sales": 11541.4, "x": 0, "y": 0}, "292": {"atlasid": "292", "color": "#3ab11a", "id": 584, "name": "大使馆和领事馆", "sales": 218.531, "x": 0, "y": 0}, "293": {"atlasid": "293", "color": "#3ab11a", "id": 585, "name": "军事单位和机构", "sales": 4415.42, "x": 0, "y": 0}, "294": {"atlasid": "294", "color": "#3ab11a", "id": 586, "name": "其他政府服务", "sales": 780.087, "x": 0, "y": 0}, "891": {"atlasid": "891", "color": "#98df8a", "id": 557, "name": "特许经营权和类似权利", "sales": 3702.51, "x": 0, "y": 0}, "892": {"atlasid": "892", "color": "#98df8a", "id": 558, "name": "其他特许权使用费和许可费", "sales": 4515.73, "x": 0, "y": 0}, "895": {"atlasid": "895", "color": "#0000ff", "id": 580, "name": "教育服务", "sales": 94.041, "x": 0, "y": 0}, "896": {"atlasid": "896", "color": "#0000ff", "id": 581, "name": "健康服务", "sales": 41.199, "x": 0, "y": 0}, "897": {"atlasid": "897", "color": "#0000ff", "id": 582, "name": "其他", "sales": 190.768, "x": 0, "y": 0}, "958": {"atlasid": "958", "color": "#D1FF00", "id": 539, "name": "邮政服务", "sales": 87.772, "x": 0, "y": 0}, "959": {"atlasid": "959", "color": "#D1FF00", "id": 540, "name": "快递服务", "sales": 104.788, "x": 0, "y": 0}, "981": {"atlasid": "981", "color": "#ffff00", "id": 588, "name": "其他服务,总计（类别总和）", "sales": 617258.0, "x": 0, "y": 0}, "982": {"atlasid": "982", "color": "#ffff00", "id": 589, "name": "商业服务,总数（类别总和）", "sales": 448265.0, "x": 0, "y": 0}, "983": {"atlasid": "983", "color": "#ffff00", "id": 590, "name": "未分配的服务", "sales": 23886.2, "x": 0, "y": 0}}, "trade": {"AE": [{"c": "JP", "e": 38393}, {"c": "IN", "e": 33464}, {"c": "SG", "e": 13527}, {"c": "KR", "e": 13362}, {"c": "CN", "e": 9545}, {"c": "PK", "e": 6579}, {"c": "OM", "e": 6306}, {"c": "MY", "e": 3743}, {"c": "TR", "e": 3589}, {"c": "HK", "e": 3349}], "AL": [{"c": "IT", "e": 956}, {"c": "ES", "e": 208}, {"c": "GR", "e": 107}, {"c": "DE", "e": 102}, {"c": "TR", "e": 101}, {"c": "CN", "e": 100}, {"c": "FR", "e": 65}, {"c": "MK", "e": 41}, {"c": "AT", "e": 38}, {"c": "IN", "e": 33}], "AO": [{"c": "CN", "e": 28678}, {"c": "IN", "e": 6951}, {"c": "ZA", "e": 2781}, {"c": "PT", "e": 2000}, {"c": "ES", "e": 1244}, {"c": "GB", "e": 1094}, {"c": "FR", "e": 1046}, {"c": "IT", "e": 767}, {"c": "NL", "e": 642}, {"c": "ID", "e": 433}], "AR": [{"c": "BR", "e": 16500}, {"c": "CN", "e": 5008}, {"c": "CL", "e": 4454}, {"c": "US", "e": 4279}, {"c": "ES", "e": 2673}, {"c": "VE", "e": 2226}, {"c": "CA", "e": 2218}, {"c": "NL", "e": 2193}, {"c": "DE", "e": 2101}, {"c": "CO", "e": 2097}], "AT": [{"c": "DE", "e": 41973}, {"c": "IT", "e": 10942}, {"c": "US", "e": 9409}, {"c": "CH", "e": 8109}, {"c": "FR", "e": 6002}, {"c": "HU", "e": 5286}, {"c": "CZ", "e": 4367}, {"c": "GB", "e": 4272}, {"c": "CN", "e": 4268}, {"c": "RU", "e": 3781}], "AU": [{"c": "CN", "e": 72479}, {"c": "JP", "e": 49001}, {"c": "KR", "e": 20784}, {"c": "IN", "e": 13113}, {"c": "US", "e": 8845}, {"c": "NZ", "e": 5847}, {"c": "HK", "e": 5742}, {"c": "TH", "e": 5211}, {"c": "ID", "e": 5153}, {"c": "SG", "e": 5017}], "AZ": [{"c": "IT", "e": 7968}, {"c": "FR", "e": 1893}, {"c": "IN", "e": 1858}, {"c": "IL", "e": 1660}, {"c": "ID", "e": 1620}, {"c": "US", "e": 1345}, {"c": "DE", "e": 1321}, {"c": "CZ", "e": 1131}, {"c": "GR", "e": 666}, {"c": "GB", "e": 646}], "BA": [{"c": "HR", "e": 774}, {"c": "DE", "e": 761}, {"c": "IT", "e": 643}, {"c": "AT", "e": 487}, {"c": "SI", "e": 454}, {"c": "TR", "e": 132}, {"c": "NL", "e": 96}, {"c": "HU", "e": 94}, {"c": "FR", "e": 93}, {"c": "MK", "e": 78}], "BD": [{"c": "US", "e": 4966}, {"c": "DE", "e": 4090}, {"c": "GB", "e": 2684}, {"c": "FR", "e": 1806}, {"c": "ES", "e": 1391}, {"c": "IT", "e": 989}, {"c": "CA", "e": 942}, {"c": "TR", "e": 752}, {"c": "NL", "e": 743}, {"c": "JP", "e": 703}], "BE": [{"c": "DE", "e": 54185}, {"c": "NL", "e": 50014}, {"c": "FR", "e": 40293}, {"c": "GB", "e": 29376}, {"c": "IT", "e": 19670}, {"c": "US", "e": 14865}, {"c": "IN", "e": 9896}, {"c": "CN", "e": 9120}, {"c": "ES", "e": 8260}, {"c": "CH", "e": 6385}], "BG": [{"c": "IT", "e": 2684}, {"c": "DE", "e": 2629}, {"c": "TR", "e": 2621}, {"c": "GR", "e": 1637}, {"c": "FR", "e": 1122}, {"c": "BE", "e": 1088}, {"c": "CN", "e": 822}, {"c": "RU", "e": 746}, {"c": "ES", "e": 677}, {"c": "US", "e": 530}], "BO": [{"c": "BR", "e": 3590}, {"c": "US", "e": 1781}, {"c": "AR", "e": 1690}, {"c": "PE", "e": 463}, {"c": "JP", "e": 445}, {"c": "CO", "e": 351}, {"c": "KR", "e": 337}, {"c": "CN", "e": 322}, {"c": "VE", "e": 304}, {"c": "CH", "e": 279}], "BR": [{"c": "CN", "e": 41280}, {"c": "US", "e": 27408}, {"c": "AR", "e": 17784}, {"c": "NL", "e": 13352}, {"c": "DE", "e": 9539}, {"c": "JP", "e": 8779}, {"c": "IN", "e": 5680}, {"c": "VE", "e": 5052}, {"c": "CL", "e": 4878}, {"c": "KR", "e": 4825}], "BY": [{"c": "RU", "e": 15027}, {"c": "NL", "e": 7550}, {"c": "UA", "e": 5564}, {"c": "LV", "e": 3236}, {"c": "DE", "e": 1768}, {"c": "PL", "e": 966}, {"c": "LT", "e": 950}, {"c": "BR", "e": 839}, {"c": "KZ", "e": 800}, {"c": "IT", "e": 674}], "CA": [{"c": "US", "e": 176852}, {"c": "CN", "e": 19818}, {"c": "JP", "e": 10118}, {"c": "GB", "e": 7624}, {"c": "MX", "e": 7091}, {"c": "DE", "e": 4497}, {"c": "KR", "e": 4453}, {"c": "NL", "e": 3724}, {"c": "FR", "e": 3707}, {"c": "BR", "e": 2823}], "CG": [{"c": "CN", "e": 3919}, {"c": "FR", "e": 948}, {"c": "AU", "e": 792}, {"c": "ES", "e": 551}, {"c": "IN", "e": 546}, {"c": "IT", "e": 284}, {"c": "MY", "e": 250}, {"c": "NL", "e": 166}, {"c": "GB", "e": 123}, {"c": "DE", "e": 80}], "CH": [{"c": "DE", "e": 45780}, {"c": "IN", "e": 27989}, {"c": "US", "e": 23321}, {"c": "HK", "e": 15594}, {"c": "FR", "e": 14961}, {"c": "IT", "e": 14170}, {"c": "GB", "e": 10466}, {"c": "CN", "e": 8694}, {"c": "JP", "e": 7628}, {"c": "TH", "e": 7282}], "CI": [{"c": "DE", "e": 1115}, {"c": "US", "e": 1080}, {"c": "NL", "e": 922}, {"c": "NG", "e": 872}, {"c": "FR", "e": 753}, {"c": "CA", "e": 446}, {"c": "BE", "e": 440}, {"c": "IN", "e": 428}, {"c": "ZA", "e": 390}, {"c": "GH", "e": 361}], "CL": [{"c": "CN", "e": 18146}, {"c": "US", "e": 9594}, {"c": "JP", "e": 8547}, {"c": "KR", "e": 4611}, {"c": "BR", "e": 4223}, {"c": "IN", "e": 2582}, {"c": "NL", "e": 2316}, {"c": "IT", "e": 2038}, {"c": "ES", "e": 1799}, {"c": "CA", "e": 1519}], "CM": [{"c": "CN", "e": 731}, {"c": "ES", "e": 551}, {"c": "PT", "e": 481}, {"c": "NL", "e": 381}, {"c": "IN", "e": 352}, {"c": "IT", "e": 331}, {"c": "FR", "e": 290}, {"c": "US", "e": 240}, {"c": "GB", "e": 189}, {"c": "BE", "e": 160}], "CN": [{"c": "US", "e": 397922}, {"c": "HK", "e": 236162}, {"c": "JP", "e": 174950}, {"c": "DE", "e": 93881}, {"c": "KR", "e": 78045}, {"c": "GB", "e": 53511}, {"c": "MX", "e": 49990}, {"c": "FR", "e": 49539}, {"c": "RU", "e": 48086}, {"c": "IN", "e": 47968}], "CO": [{"c": "US", "e": 22452}, {"c": "CN", "e": 3345}, {"c": "ES", "e": 3114}, {"c": "NL", "e": 3083}, {"c": "PA", "e": 2910}, {"c": "VE", "e": 2500}, {"c": "CL", "e": 2194}, {"c": "EC", "e": 1992}, {"c": "PE", "e": 1592}, {"c": "GB", "e": 1590}], "CR": [{"c": "US", "e": 9732}, {"c": "NL", "e": 2662}, {"c": "MX", "e": 2189}, {"c": "CN", "e": 1237}, {"c": "MY", "e": 625}, {"c": "PA", "e": 584}, {"c": "HK", "e": 574}, {"c": "NI", "e": 481}, {"c": "GT", "e": 467}, {"c": "CA", "e": 424}], "CU": [{"c": "CN", "e": 534}, {"c": "ES", "e": 193}, {"c": "BR", "e": 90}, {"c": "BE", "e": 88}, {"c": "IT", "e": 56}, {"c": "DE", "e": 56}, {"c": "GB", "e": 52}, {"c": "BY", "e": 51}, {"c": "PL", "e": 50}, {"c": "FR", "e": 46}], "CZ": [{"c": "DE", "e": 42642}, {"c": "SK", "e": 10657}, {"c": "PL", "e": 7605}, {"c": "FR", "e": 7565}, {"c": "GB", "e": 7133}, {"c": "AT", "e": 6552}, {"c": "NL", "e": 6083}, {"c": "RU", "e": 5987}, {"c": "IT", "e": 5423}, {"c": "BE", "e": 4000}], "DE": [{"c": "FR", "e": 116463}, {"c": "US", "e": 107601}, {"c": "CN", "e": 83982}, {"c": "GB", "e": 82134}, {"c": "NL", "e": 77214}, {"c": "IT", "e": 68282}, {"c": "BE", "e": 63297}, {"c": "AT", "e": 62791}, {"c": "CH", "e": 59492}, {"c": "RU", "e": 46504}], "DK": [{"c": "SE", "e": 12958}, {"c": "DE", "e": 12757}, {"c": "GB", "e": 9224}, {"c": "US", "e": 7461}, {"c": "NO", "e": 5513}, {"c": "NL", "e": 4119}, {"c": "FR", "e": 3389}, {"c": "CN", "e": 3002}, {"c": "IT", "e": 2781}, {"c": "JP", "e": 2298}], "DO": [{"c": "US", "e": 4339}, {"c": "CN", "e": 401}, {"c": "CA", "e": 206}, {"c": "GB", "e": 199}, {"c": "DE", "e": 184}, {"c": "NL", "e": 163}, {"c": "ES", "e": 142}, {"c": "BE", "e": 142}, {"c": "GT", "e": 119}, {"c": "KR", "e": 113}], "DZ": [{"c": "IT", "e": 10657}, {"c": "US", "e": 10166}, {"c": "ES", "e": 8340}, {"c": "FR", "e": 5232}, {"c": "CA", "e": 5176}, {"c": "NL", "e": 5125}, {"c": "BR", "e": 3273}, {"c": "TR", "e": 3180}, {"c": "GB", "e": 3063}, {"c": "CN", "e": 2557}], "EC": [{"c": "US", "e": 10234}, {"c": "PE", "e": 2022}, {"c": "CL", "e": 1943}, {"c": "CO", "e": 1084}, {"c": "VE", "e": 1008}, {"c": "PA", "e": 923}, {"c": "JP", "e": 831}, {"c": "RU", "e": 783}, {"c": "ES", "e": 521}, {"c": "DE", "e": 498}], "EE": [{"c": "RU", "e": 2790}, {"c": "SE", "e": 2234}, {"c": "FI", "e": 1831}, {"c": "US", "e": 1214}, {"c": "LV", "e": 1027}, {"c": "LT", "e": 818}, {"c": "DE", "e": 674}, {"c": "NO", "e": 599}, {"c": "GB", "e": 395}, {"c": "NL", "e": 385}], "EG": [{"c": "IT", "e": 2946}, {"c": "US", "e": 2897}, {"c": "IN", "e": 2370}, {"c": "DE", "e": 1732}, {"c": "SA", "e": 1708}, {"c": "TR", "e": 1653}, {"c": "FR", "e": 1643}, {"c": "ES", "e": 1430}, {"c": "CN", "e": 1196}, {"c": "JP", "e": 1143}], "ES": [{"c": "FR", "e": 40413}, {"c": "DE", "e": 27344}, {"c": "IT", "e": 20736}, {"c": "PT", "e": 19101}, {"c": "GB", "e": 16740}, {"c": "US", "e": 11880}, {"c": "NL", "e": 8632}, {"c": "BE", "e": 8243}, {"c": "TR", "e": 6305}, {"c": "CH", "e": 5897}], "ET": [{"c": "CN", "e": 323}, {"c": "DE", "e": 285}, {"c": "CH", "e": 210}, {"c": "SA", "e": 192}, {"c": "BE", "e": 174}, {"c": "US", "e": 134}, {"c": "NL", "e": 105}, {"c": "AE", "e": 80}, {"c": "IT", "e": 79}, {"c": "GB", "e": 73}], "FI": [{"c": "SE", "e": 7968}, {"c": "DE", "e": 6964}, {"c": "RU", "e": 6748}, {"c": "US", "e": 5119}, {"c": "NL", "e": 4526}, {"c": "GB", "e": 3571}, {"c": "CN", "e": 3538}, {"c": "FR", "e": 2355}, {"c": "NO", "e": 2353}, {"c": "BE", "e": 2290}], "FR": [{"c": "DE", "e": 78795}, {"c": "BE", "e": 46557}, {"c": "IT", "e": 37644}, {"c": "US", "e": 36480}, {"c": "GB", "e": 35010}, {"c": "ES", "e": 34272}, {"c": "NL", "e": 21962}, {"c": "CN", "e": 19506}, {"c": "CH", "e": 15321}, {"c": "RU", "e": 12246}], "GA": [{"c": "JP", "e": 2342}, {"c": "AU", "e": 991}, {"c": "IN", "e": 740}, {"c": "CN", "e": 538}, {"c": "ES", "e": 412}, {"c": "KR", "e": 266}, {"c": "IT", "e": 197}, {"c": "MY", "e": 159}, {"c": "DE", "e": 133}, {"c": "FR", "e": 127}], "GB": [{"c": "US", "e": 52367}, {"c": "DE", "e": 47488}, {"c": "NL", "e": 32919}, {"c": "FR", "e": 29837}, {"c": "BE", "e": 24032}, {"c": "CN", "e": 16117}, {"c": "ES", "e": 12846}, {"c": "IT", "e": 12224}, {"c": "SE", "e": 9885}, {"c": "RU", "e": 8161}], "GE": [{"c": "AZ", "e": 617}, {"c": "US", "e": 236}, {"c": "DE", "e": 223}, {"c": "CA", "e": 192}, {"c": "BG", "e": 188}, {"c": "UA", "e": 178}, {"c": "TR", "e": 167}, {"c": "LB", "e": 148}, {"c": "RU", "e": 86}, {"c": "BE", "e": 72}], "GH": [{"c": "ZA", "e": 4441}, {"c": "AE", "e": 1633}, {"c": "CH", "e": 1302}, {"c": "FR", "e": 1203}, {"c": "IT", "e": 1099}, {"c": "NL", "e": 815}, {"c": "CN", "e": 629}, {"c": "DE", "e": 468}, {"c": "GB", "e": 415}, {"c": "US", "e": 358}], "GN": [{"c": "IN", "e": 183}, {"c": "ES", "e": 171}, {"c": "CL", "e": 169}, {"c": "US", "e": 120}, {"c": "DE", "e": 116}, {"c": "UA", "e": 101}, {"c": "FR", "e": 95}, {"c": "RU", "e": 63}, {"c": "CA", "e": 62}, {"c": "BE", "e": 31}], "GR": [{"c": "TR", "e": 3566}, {"c": "IT", "e": 2694}, {"c": "DE", "e": 2176}, {"c": "BG", "e": 1677}, {"c": "US", "e": 1368}, {"c": "GB", "e": 1105}, {"c": "LB", "e": 922}, {"c": "ES", "e": 895}, {"c": "FR", "e": 868}, {"c": "MK", "e": 821}], "GT": [{"c": "US", "e": 4976}, {"c": "SV", "e": 1031}, {"c": "HN", "e": 743}, {"c": "MX", "e": 633}, {"c": "CR", "e": 430}, {"c": "NI", "e": 425}, {"c": "CA", "e": 352}, {"c": "PA", "e": 247}, {"c": "CL", "e": 197}, {"c": "JP", "e": 196}], "HK": [{"c": "CN", "e": 61599}, {"c": "MY", "e": 4262}, {"c": "US", "e": 4129}, {"c": "IN", "e": 4021}, {"c": "GB", "e": 3704}, {"c": "VN", "e": 3332}, {"c": "AE", "e": 3103}, {"c": "SG", "e": 2534}, {"c": "CH", "e": 2529}, {"c": "NL", "e": 2494}], "HN": [{"c": "US", "e": 5091}, {"c": "DE", "e": 501}, {"c": "SV", "e": 451}, {"c": "GT", "e": 364}, {"c": "MX", "e": 306}, {"c": "CN", "e": 284}, {"c": "CA", "e": 199}, {"c": "BE", "e": 190}, {"c": "NI", "e": 176}, {"c": "NL", "e": 167}], "HR": [{"c": "IT", "e": 1773}, {"c": "BA", "e": 1447}, {"c": "DE", "e": 1245}, {"c": "SI", "e": 1065}, {"c": "AT", "e": 877}, {"c": "RU", "e": 491}, {"c": "US", "e": 416}, {"c": "HU", "e": 312}, {"c": "BE", "e": 269}, {"c": "NL", "e": 210}], "HU": [{"c": "DE", "e": 23107}, {"c": "AT", "e": 4924}, {"c": "IT", "e": 4429}, {"c": "FR", "e": 4341}, {"c": "GB", "e": 4170}, {"c": "SK", "e": 3773}, {"c": "CZ", "e": 3392}, {"c": "RU", "e": 3301}, {"c": "PL", "e": 3296}, {"c": "US", "e": 2732}], "ID": [{"c": "JP", "e": 32165}, {"c": "CN", "e": 26108}, {"c": "SG", "e": 19275}, {"c": "US", "e": 17881}, {"c": "KR", "e": 15301}, {"c": "IN", "e": 12852}, {"c": "MY", "e": 11334}, {"c": "TH", "e": 7645}, {"c": "AU", "e": 6312}, {"c": "DE", "e": 4931}], "IL": [{"c": "US", "e": 9554}, {"c": "GB", "e": 3545}, {"c": "NL", "e": 2688}, {"c": "CN", "e": 2115}, {"c": "IN", "e": 2087}, {"c": "DE", "e": 1760}, {"c": "TR", "e": 1615}, {"c": "FR", "e": 1233}, {"c": "RU", "e": 1217}, {"c": "IT", "e": 1203}], "IN": [{"c": "US", "e": 33806}, {"c": "AE", "e": 31963}, {"c": "CN", "e": 16061}, {"c": "SG", "e": 12340}, {"c": "GB", "e": 9168}, {"c": "DE", "e": 8884}, {"c": "SA", "e": 8521}, {"c": "KR", "e": 6559}, {"c": "JP", "e": 6380}, {"c": "NL", "e": 6149}], "IR": [{"c": "CN", "e": 21808}, {"c": "IN", "e": 11852}, {"c": "KR", "e": 7498}, {"c": "JP", "e": 6916}, {"c": "IT", "e": 2558}, {"c": "GR", "e": 1758}, {"c": "SG", "e": 1695}, {"c": "TR", "e": 1287}, {"c": "ZA", "e": 1230}, {"c": "ES", "e": 850}], "IT": [{"c": "DE", "e": 56910}, {"c": "FR", "e": 49005}, {"c": "US", "e": 35546}, {"c": "CH", "e": 27575}, {"c": "GB", "e": 22618}, {"c": "ES", "e": 20383}, {"c": "BE", "e": 13869}, {"c": "TR", "e": 13414}, {"c": "RU", "e": 12638}, {"c": "CN", "e": 12265}], "JO": [{"c": "US", "e": 1166}, {"c": "IN", "e": 1091}, {"c": "SA", "e": 765}, {"c": "LB", "e": 343}, {"c": "AE", "e": 316}, {"c": "ID", "e": 287}, {"c": "CN", "e": 269}, {"c": "EG", "e": 223}, {"c": "SY", "e": 218}, {"c": "IL", "e": 214}], "JP": [{"c": "CN", "e": 147415}, {"c": "US", "e": 140105}, {"c": "KR", "e": 62023}, {"c": "TH", "e": 43065}, {"c": "HK", "e": 34276}, {"c": "DE", "e": 26509}, {"c": "ID", "e": 20395}, {"c": "AU", "e": 19632}, {"c": "SG", "e": 19345}, {"c": "MY", "e": 17221}], "KE": [{"c": "UG", "e": 551}, {"c": "TZ", "e": 550}, {"c": "NL", "e": 470}, {"c": "GB", "e": 450}, {"c": "US", "e": 374}, {"c": "EG", "e": 276}, {"c": "PK", "e": 225}, {"c": "DE", "e": 130}, {"c": "RU", "e": 130}, {"c": "IT", "e": 103}], "KG": [{"c": "CH", "e": 549}, {"c": "KZ", "e": 324}, {"c": "RU", "e": 222}, {"c": "UZ", "e": 182}, {"c": "CN", "e": 71}, {"c": "TR", "e": 67}, {"c": "TJ", "e": 40}, {"c": "FR", "e": 33}, {"c": "DE", "e": 20}, {"c": "BE", "e": 18}], "KH": [{"c": "US", "e": 3321}, {"c": "HK", "e": 1725}, {"c": "GB", "e": 950}, {"c": "DE", "e": 945}, {"c": "CA", "e": 626}, {"c": "SG", "e": 556}, {"c": "JP", "e": 479}, {"c": "VN", "e": 310}, {"c": "TH", "e": 275}, {"c": "FR", "e": 270}], "KR": [{"c": "CN", "e": 131455}, {"c": "US", "e": 62881}, {"c": "JP", "e": 38951}, {"c": "HK", "e": 27012}, {"c": "SG", "e": 25593}, {"c": "VN", "e": 15215}, {"c": "IN", "e": 13085}, {"c": "ID", "e": 12919}, {"c": "MX", "e": 11644}, {"c": "RU", "e": 11163}], "KW": [{"c": "KR", "e": 15964}, {"c": "IN", "e": 15813}, {"c": "JP", "e": 13333}, {"c": "CN", "e": 9211}, {"c": "SG", "e": 4221}, {"c": "PK", "e": 3779}, {"c": "NL", "e": 2664}, {"c": "EG", "e": 2434}, {"c": "GB", "e": 2044}, {"c": "ID", "e": 1975}], "KZ": [{"c": "CN", "e": 16407}, {"c": "RU", "e": 7562}, {"c": "IT", "e": 7291}, {"c": "NL", "e": 6191}, {"c": "FR", "e": 5783}, {"c": "AT", "e": 3646}, {"c": "CH", "e": 3448}, {"c": "TR", "e": 3341}, {"c": "CA", "e": 3075}, {"c": "DE", "e": 2666}], "LA": [{"c": "CN", "e": 740}, {"c": "TH", "e": 661}, {"c": "IN", "e": 135}, {"c": "JP", "e": 120}, {"c": "GB", "e": 103}, {"c": "DE", "e": 79}, {"c": "VN", "e": 49}, {"c": "AU", "e": 46}, {"c": "NL", "e": 37}, {"c": "IT", "e": 25}], "LB": [{"c": "ZA", "e": 868}, {"c": "CH", "e": 856}, {"c": "SA", "e": 351}, {"c": "AE", "e": 346}, {"c": "SY", "e": 294}, {"c": "JO", "e": 157}, {"c": "TR", "e": 144}, {"c": "BE", "e": 121}, {"c": "EG", "e": 99}, {"c": "NG", "e": 70}], "LK": [{"c": "US", "e": 2182}, {"c": "GB", "e": 1158}, {"c": "IN", "e": 665}, {"c": "DE", "e": 600}, {"c": "IT", "e": 478}, {"c": "RU", "e": 331}, {"c": "BE", "e": 304}, {"c": "JP", "e": 269}, {"c": "FR", "e": 267}, {"c": "AE", "e": 222}], "LR": [{"c": "CN", "e": 190}, {"c": "PL", "e": 144}, {"c": "US", "e": 136}, {"c": "ES", "e": 93}, {"c": "DZ", "e": 62}, {"c": "MY", "e": 33}, {"c": "CA", "e": 32}, {"c": "FR", "e": 28}, {"c": "GR", "e": 24}, {"c": "IL", "e": 23}], "LT": [{"c": "RU", "e": 4187}, {"c": "LV", "e": 2807}, {"c": "DE", "e": 2181}, {"c": "NL", "e": 1778}, {"c": "FR", "e": 1429}, {"c": "GB", "e": 1425}, {"c": "EE", "e": 1300}, {"c": "PL", "e": 1174}, {"c": "UA", "e": 1016}, {"c": "SE", "e": 949}], "LV": [{"c": "LT", "e": 1821}, {"c": "RU", "e": 1332}, {"c": "EE", "e": 964}, {"c": "DE", "e": 860}, {"c": "SE", "e": 697}, {"c": "NL", "e": 617}, {"c": "GB", "e": 526}, {"c": "DK", "e": 476}, {"c": "NO", "e": 473}, {"c": "PL", "e": 422}], "MA": [{"c": "FR", "e": 4462}, {"c": "ES", "e": 3849}, {"c": "BR", "e": 1453}, {"c": "IN", "e": 1373}, {"c": "IT", "e": 975}, {"c": "DE", "e": 937}, {"c": "US", "e": 923}, {"c": "BE", "e": 790}, {"c": "GB", "e": 737}, {"c": "NL", "e": 676}], "MD": [{"c": "RU", "e": 759}, {"c": "IT", "e": 254}, {"c": "UA", "e": 162}, {"c": "TR", "e": 99}, {"c": "DE", "e": 96}, {"c": "PL", "e": 84}, {"c": "GB", "e": 83}, {"c": "BY", "e": 82}, {"c": "KZ", "e": 51}, {"c": "FR", "e": 42}], "MG": [{"c": "FR", "e": 425}, {"c": "DE", "e": 124}, {"c": "CN", "e": 115}, {"c": "US", "e": 109}, {"c": "SG", "e": 92}, {"c": "IN", "e": 84}, {"c": "CA", "e": 81}, {"c": "ZA", "e": 76}, {"c": "ES", "e": 68}, {"c": "ID", "e": 60}], "MK": [{"c": "DE", "e": 1203}, {"c": "BG", "e": 311}, {"c": "IT", "e": 286}, {"c": "CZ", "e": 198}, {"c": "GR", "e": 184}, {"c": "CN", "e": 167}, {"c": "HR", "e": 105}, {"c": "TR", "e": 102}, {"c": "BA", "e": 91}, {"c": "CH", "e": 77}], "ML": [{"c": "ZA", "e": 1356}, {"c": "CN", "e": 478}, {"c": "CH", "e": 302}, {"c": "CI", "e": 74}, {"c": "MY", "e": 65}, {"c": "SN", "e": 62}, {"c": "FR", "e": 58}, {"c": "IN", "e": 41}, {"c": "ID", "e": 37}, {"c": "SA", "e": 34}], "MN": [{"c": "CN", "e": 3460}, {"c": "CA", "e": 166}, {"c": "RU", "e": 57}, {"c": "KR", "e": 53}, {"c": "IT", "e": 46}, {"c": "JP", "e": 21}, {"c": "DE", "e": 13}, {"c": "IN", "e": 11}, {"c": "GB", "e": 11}, {"c": "US", "e": 8}], "MR": [{"c": "CN", "e": 1566}, {"c": "CH", "e": 282}, {"c": "IT", "e": 268}, {"c": "JP", "e": 214}, {"c": "DE", "e": 201}, {"c": "ES", "e": 148}, {"c": "FR", "e": 138}, {"c": "GH", "e": 77}, {"c": "AE", "e": 73}, {"c": "CI", "e": 66}], "MU": [{"c": "GB", "e": 417}, {"c": "FR", "e": 375}, {"c": "ZA", "e": 224}, {"c": "US", "e": 219}, {"c": "IT", "e": 199}, {"c": "ES", "e": 178}, {"c": "MG", "e": 111}, {"c": "CH", "e": 51}, {"c": "DE", "e": 51}, {"c": "NL", "e": 44}], "MW": [{"c": "CA", "e": 109}, {"c": "DE", "e": 96}, {"c": "RU", "e": 71}, {"c": "ZA", "e": 70}, {"c": "US", "e": 66}, {"c": "CN", "e": 45}, {"c": "ZW", "e": 43}, {"c": "IN", "e": 39}, {"c": "PL", "e": 39}, {"c": "NL", "e": 37}], "MX": [{"c": "US", "e": 244951}, {"c": "CA", "e": 18967}, {"c": "ES", "e": 7405}, {"c": "CN", "e": 6942}, {"c": "CO", "e": 6211}, {"c": "BR", "e": 5952}, {"c": "DE", "e": 5367}, {"c": "JP", "e": 3927}, {"c": "IN", "e": 3508}, {"c": "GB", "e": 3144}], "MY": [{"c": "SG", "e": 31005}, {"c": "JP", "e": 29637}, {"c": "CN", "e": 29585}, {"c": "US", "e": 17465}, {"c": "TH", "e": 12195}, {"c": "ID", "e": 11399}, {"c": "AU", "e": 9778}, {"c": "IN", "e": 9502}, {"c": "KR", "e": 9397}, {"c": "NL", "e": 7512}], "MZ": [{"c": "ZA", "e": 1231}, {"c": "NL", "e": 923}, {"c": "CN", "e": 784}, {"c": "BE", "e": 560}, {"c": "IT", "e": 339}, {"c": "IN", "e": 290}, {"c": "ES", "e": 264}, {"c": "GB", "e": 248}, {"c": "DE", "e": 139}, {"c": "CH", "e": 134}], "NG": [{"c": "US", "e": 21056}, {"c": "IN", "e": 14029}, {"c": "ES", "e": 9009}, {"c": "BR", "e": 8190}, {"c": "ZA", "e": 6218}, {"c": "GB", "e": 6124}, {"c": "NL", "e": 5692}, {"c": "FR", "e": 5102}, {"c": "DE", "e": 5033}, {"c": "JP", "e": 4263}], "NI": [{"c": "US", "e": 1367}, {"c": "VE", "e": 443}, {"c": "CA", "e": 367}, {"c": "SV", "e": 248}, {"c": "CR", "e": 146}, {"c": "MX", "e": 128}, {"c": "CN", "e": 106}, {"c": "GT", "e": 93}, {"c": "IN", "e": 67}, {"c": "HN", "e": 65}], "NL": [{"c": "DE", "e": 97669}, {"c": "BE", "e": 80986}, {"c": "GB", "e": 46204}, {"c": "FR", "e": 29998}, {"c": "IT", "e": 25704}, {"c": "US", "e": 20573}, {"c": "ES", "e": 14032}, {"c": "SE", "e": 10251}, {"c": "CN", "e": 9512}, {"c": "PL", "e": 7673}], "NO": [{"c": "GB", "e": 34043}, {"c": "DE", "e": 20799}, {"c": "NL", "e": 15545}, {"c": "SE", "e": 12023}, {"c": "FR", "e": 10927}, {"c": "US", "e": 6905}, {"c": "DK", "e": 6356}, {"c": "BE", "e": 6180}, {"c": "KR", "e": 5040}, {"c": "CA", "e": 2985}], "NZ": [{"c": "AU", "e": 7331}, {"c": "CN", "e": 5585}, {"c": "US", "e": 3411}, {"c": "JP", "e": 2876}, {"c": "GB", "e": 1265}, {"c": "KR", "e": 1260}, {"c": "IN", "e": 817}, {"c": "MY", "e": 777}, {"c": "DE", "e": 741}, {"c": "ID", "e": 708}], "OM": [{"c": "CN", "e": 14827}, {"c": "JP", "e": 5998}, {"c": "KR", "e": 4718}, {"c": "SG", "e": 2069}, {"c": "IN", "e": 1944}, {"c": "AE", "e": 1853}, {"c": "SA", "e": 998}, {"c": "US", "e": 990}, {"c": "NZ", "e": 812}, {"c": "PK", "e": 736}], "PA": [{"c": "EC", "e": 1590}, {"c": "KR", "e": 539}, {"c": "GT", "e": 524}, {"c": "CR", "e": 523}, {"c": "US", "e": 260}, {"c": "ID", "e": 205}, {"c": "SV", "e": 176}, {"c": "GR", "e": 121}, {"c": "CA", "e": 119}, {"c": "NL", "e": 82}], "PE": [{"c": "CN", "e": 7892}, {"c": "US", "e": 6552}, {"c": "CH", "e": 5125}, {"c": "CA", "e": 3557}, {"c": "JP", "e": 2629}, {"c": "CL", "e": 2040}, {"c": "DE", "e": 1972}, {"c": "ES", "e": 1926}, {"c": "KR", "e": 1561}, {"c": "BR", "e": 1391}], "PG": [{"c": "AU", "e": 4848}, {"c": "JP", "e": 1445}, {"c": "CN", "e": 639}, {"c": "DE", "e": 523}, {"c": "PH", "e": 210}, {"c": "KR", "e": 206}, {"c": "NL", "e": 198}, {"c": "GB", "e": 174}, {"c": "IT", "e": 163}, {"c": "ES", "e": 148}], "PH": [{"c": "CN", "e": 16634}, {"c": "JP", "e": 9470}, {"c": "US", "e": 8850}, {"c": "HK", "e": 7042}, {"c": "SG", "e": 3879}, {"c": "KR", "e": 3437}, {"c": "TH", "e": 2885}, {"c": "DE", "e": 2848}, {"c": "MY", "e": 1699}, {"c": "NL", "e": 1513}], "PK": [{"c": "US", "e": 3529}, {"c": "CN", "e": 3016}, {"c": "DE", "e": 1259}, {"c": "GB", "e": 1230}, {"c": "AE", "e": 1077}, {"c": "KR", "e": 750}, {"c": "FR", "e": 616}, {"c": "IT", "e": 568}, {"c": "TR", "e": 560}, {"c": "ES", "e": 521}], "PL": [{"c": "DE", "e": 40319}, {"c": "GB", "e": 11456}, {"c": "FR", "e": 10433}, {"c": "CZ", "e": 9997}, {"c": "RU", "e": 9069}, {"c": "IT", "e": 9045}, {"c": "NL", "e": 7481}, {"c": "SE", "e": 4508}, {"c": "US", "e": 4436}, {"c": "UA", "e": 4373}], "PT": [{"c": "ES", "e": 11347}, {"c": "FR", "e": 6355}, {"c": "DE", "e": 6110}, {"c": "AO", "e": 3855}, {"c": "GB", "e": 2739}, {"c": "US", "e": 2555}, {"c": "NL", "e": 2348}, {"c": "BE", "e": 2213}, {"c": "IT", "e": 2096}, {"c": "CN", "e": 1284}], "PY": [{"c": "BR", "e": 1042}, {"c": "RU", "e": 712}, {"c": "DE", "e": 417}, {"c": "US", "e": 263}, {"c": "IT", "e": 224}, {"c": "CL", "e": 192}, {"c": "PE", "e": 185}, {"c": "ES", "e": 173}, {"c": "IL", "e": 133}, {"c": "AR", "e": 133}], "RU": [{"c": "NL", "e": 43369}, {"c": "CN", "e": 38153}, {"c": "DE", "e": 30489}, {"c": "UA", "e": 26674}, {"c": "BY", "e": 25467}, {"c": "IT", "e": 23286}, {"c": "PL", "e": 21068}, {"c": "JP", "e": 17340}, {"c": "KZ", "e": 15982}, {"c": "TR", "e": 15032}], "SA": [{"c": "CN", "e": 48274}, {"c": "JP", "e": 47580}, {"c": "KR", "e": 34535}, {"c": "IN", "e": 29167}, {"c": "SG", "e": 15325}, {"c": "IT", "e": 8516}, {"c": "ZA", "e": 7854}, {"c": "ES", "e": 6888}, {"c": "FR", "e": 6249}, {"c": "NL", "e": 5348}], "SE": [{"c": "DE", "e": 16241}, {"c": "GB", "e": 13595}, {"c": "NO", "e": 12365}, {"c": "DK", "e": 11439}, {"c": "US", "e": 10376}, {"c": "NL", "e": 8704}, {"c": "BE", "e": 8395}, {"c": "FR", "e": 7540}, {"c": "FI", "e": 7274}, {"c": "CN", "e": 6127}], "SG": [{"c": "CN", "e": 30770}, {"c": "MY", "e": 26311}, {"c": "ID", "e": 26091}, {"c": "HK", "e": 16824}, {"c": "AU", "e": 13537}, {"c": "KR", "e": 10025}, {"c": "US", "e": 8472}, {"c": "IN", "e": 7789}, {"c": "JP", "e": 6938}, {"c": "TH", "e": 6559}], "SI": [{"c": "DE", "e": 5643}, {"c": "IT", "e": 3223}, {"c": "AT", "e": 2147}, {"c": "FR", "e": 1560}, {"c": "RU", "e": 1255}, {"c": "HR", "e": 1185}, {"c": "HU", "e": 835}, {"c": "PL", "e": 757}, {"c": "CZ", "e": 678}, {"c": "BA", "e": 592}], "SK": [{"c": "DE", "e": 15886}, {"c": "CZ", "e": 8786}, {"c": "PL", "e": 4803}, {"c": "AT", "e": 4379}, {"c": "HU", "e": 4153}, {"c": "FR", "e": 3974}, {"c": "RU", "e": 3588}, {"c": "IT", "e": 3521}, {"c": "GB", "e": 2918}, {"c": "CN", "e": 2107}], "SN": [{"c": "ML", "e": 723}, {"c": "IN", "e": 344}, {"c": "CH", "e": 340}, {"c": "GN", "e": 122}, {"c": "FR", "e": 102}, {"c": "IT", "e": 101}, {"c": "ES", "e": 89}, {"c": "MR", "e": 87}, {"c": "CI", "e": 87}, {"c": "GH", "e": 72}], "SV": [{"c": "US", "e": 2539}, {"c": "GT", "e": 734}, {"c": "HN", "e": 719}, {"c": "NI", "e": 313}, {"c": "CR", "e": 237}, {"c": "PA", "e": 124}, {"c": "DE", "e": 97}, {"c": "MX", "e": 88}, {"c": "ES", "e": 81}, {"c": "DO", "e": 80}], "SY": [{"c": "LB", "e": 252}, {"c": "JO", "e": 230}, {"c": "EG", "e": 227}, {"c": "IN", "e": 146}, {"c": "DE", "e": 99}, {"c": "IT", "e": 76}, {"c": "TR", "e": 64}, {"c": "YE", "e": 51}, {"c": "DZ", "e": 45}, {"c": "UA", "e": 38}], "TH": [{"c": "CN", "e": 30836}, {"c": "JP", "e": 22549}, {"c": "US", "e": 21205}, {"c": "ID", "e": 11356}, {"c": "MY", "e": 10966}, {"c": "AU", "e": 10464}, {"c": "HK", "e": 9725}, {"c": "SG", "e": 8626}, {"c": "IN", "e": 5729}, {"c": "VN", "e": 5377}], "TJ": [{"c": "TR", "e": 333}, {"c": "CN", "e": 102}, {"c": "GR", "e": 67}, {"c": "KZ", "e": 65}, {"c": "RU", "e": 64}, {"c": "IT", "e": 46}, {"c": "NO", "e": 32}, {"c": "US", "e": 26}, {"c": "IN", "e": 15}, {"c": "DZ", "e": 15}], "TM": [{"c": "CN", "e": 7581}, {"c": "IT", "e": 493}, {"c": "TR", "e": 295}, {"c": "RU", "e": 176}, {"c": "KZ", "e": 159}, {"c": "UA", "e": 115}, {"c": "GB", "e": 107}, {"c": "DE", "e": 78}, {"c": "AL", "e": 68}, {"c": "BG", "e": 52}], "TN": [{"c": "FR", "e": 4648}, {"c": "IT", "e": 2842}, {"c": "DE", "e": 1817}, {"c": "ES", "e": 695}, {"c": "GB", "e": 495}, {"c": "BE", "e": 472}, {"c": "NL", "e": 460}, {"c": "DZ", "e": 434}, {"c": "US", "e": 288}, {"c": "EG", "e": 282}], "TR": [{"c": "DE", "e": 14775}, {"c": "IR", "e": 9818}, {"c": "GB", "e": 8741}, {"c": "AE", "e": 8118}, {"c": "FR", "e": 7129}, {"c": "RU", "e": 6770}, {"c": "IT", "e": 6768}, {"c": "US", "e": 6178}, {"c": "ES", "e": 3957}, {"c": "EG", "e": 3806}], "TT": [{"c": "US", "e": 3086}, {"c": "AR", "e": 1708}, {"c": "CL", "e": 1297}, {"c": "ES", "e": 811}, {"c": "BR", "e": 620}, {"c": "KR", "e": 511}, {"c": "CO", "e": 466}, {"c": "FR", "e": 311}, {"c": "JP", "e": 164}, {"c": "NL", "e": 144}], "TZ": [{"c": "ZA", "e": 1073}, {"c": "CH", "e": 811}, {"c": "IN", "e": 476}, {"c": "CN", "e": 463}, {"c": "KE", "e": 348}, {"c": "DE", "e": 234}, {"c": "JP", "e": 231}, {"c": "US", "e": 128}, {"c": "NL", "e": 123}, {"c": "MW", "e": 104}], "UA": [{"c": "RU", "e": 17731}, {"c": "EG", "e": 4751}, {"c": "TR", "e": 3798}, {"c": "IT", "e": 2758}, {"c": "KZ", "e": 2522}, {"c": "PL", "e": 2492}, {"c": "IN", "e": 2480}, {"c": "BY", "e": 2019}, {"c": "CN", "e": 1849}, {"c": "DE", "e": 1740}], "UG": [{"c": "KE", "e": 227}, {"c": "AE", "e": 174}, {"c": "NL", "e": 138}, {"c": "DE", "e": 114}, {"c": "TZ", "e": 108}, {"c": "IT", "e": 81}, {"c": "BE", "e": 68}, {"c": "GB", "e": 57}, {"c": "SG", "e": 55}, {"c": "ES", "e": 52}], "US": [{"c": "CA", "e": 158983}, {"c": "MX", "e": 137844}, {"c": "CN", "e": 113555}, {"c": "JP", "e": 67031}, {"c": "DE", "e": 59913}, {"c": "GB", "e": 42733}, {"c": "KR", "e": 41472}, {"c": "FR", "e": 38513}, {"c": "NL", "e": 33224}, {"c": "BR", "e": 31704}], "UY": [{"c": "BR", "e": 1709}, {"c": "CN", "e": 1071}, {"c": "AR", "e": 516}, {"c": "VE", "e": 417}, {"c": "RU", "e": 395}, {"c": "US", "e": 352}, {"c": "DE", "e": 352}, {"c": "CL", "e": 247}, {"c": "IL", "e": 234}, {"c": "MX", "e": 231}], "UZ": [{"c": "RU", "e": 1337}, {"c": "CN", "e": 1042}, {"c": "TR", "e": 796}, {"c": "KZ", "e": 774}, {"c": "FR", "e": 156}, {"c": "JP", "e": 106}, {"c": "UA", "e": 104}, {"c": "KG", "e": 59}, {"c": "GB", "e": 42}, {"c": "KR", "e": 40}], "VE": [{"c": "CN", "e": 12504}, {"c": "IN", "e": 10325}, {"c": "SG", "e": 3351}, {"c": "ES", "e": 1497}, {"c": "US", "e": 970}, {"c": "BR", "e": 860}, {"c": "NI", "e": 735}, {"c": "UY", "e": 723}, {"c": "GB", "e": 637}, {"c": "MY", "e": 637}], "VN": [{"c": "US", "e": 17710}, {"c": "JP", "e": 14042}, {"c": "CN", "e": 13742}, {"c": "DE", "e": 6357}, {"c": "KR", "e": 5619}, {"c": "HK", "e": 4165}, {"c": "MY", "e": 3996}, {"c": "GB", "e": 3832}, {"c": "FR", "e": 3319}, {"c": "AU", "e": 3166}], "YE": [{"c": "CN", "e": 3081}, {"c": "TH", "e": 1470}, {"c": "KR", "e": 943}, {"c": "IN", "e": 909}, {"c": "JP", "e": 327}, {"c": "SA", "e": 248}, {"c": "SG", "e": 198}, {"c": "MY", "e": 131}, {"c": "US", "e": 126}, {"c": "CH", "e": 96}], "ZA": [{"c": "CN", "e": 9684}, {"c": "US", "e": 9353}, {"c": "IN", "e": 9095}, {"c": "GB", "e": 8340}, {"c": "JP", "e": 6328}, {"c": "HK", "e": 5838}, {"c": "DE", "e": 5694}, {"c": "BE", "e": 3635}, {"c": "ZW", "e": 2996}, {"c": "ZM", "e": 2759}], "ZM": [{"c": "CN", "e": 2581}, {"c": "ZA", "e": 536}, {"c": "ZW", "e": 459}, {"c": "KR", "e": 322}, {"c": "EG", "e": 297}, {"c": "IN", "e": 283}, {"c": "IT", "e": 221}, {"c": "GB", "e": 62}, {"c": "JP", "e": 49}, {"c": "TH", "e": 46}], "ZW": [{"c": "ZA", "e": 1447}, {"c": "AE", "e": 482}, {"c": "CN", "e": 371}, {"c": "MZ", "e": 240}, {"c": "IT", "e": 115}, {"c": "ZM", "e": 97}, {"c": "NL", "e": 69}, {"c": "PT", "e": 56}, {"c": "DE", "e": 53}, {"c": "US", "e": 48}]}}